Workbook

Sheet Derived Rates
A1: Irish Derived Cost Build-up — Spon's Civil Engineering Rates
A2: Cost of each item derived from Labour + Plant + Material (+ Sub-contract where the source publishes an all-in specialist rate), then converted to Irish costs in euro using the factors on the 'Irish Basis' sheet. IRISH COST € (column R) is the deliverable; UK COST £ (column M) is the build-up it derives from. Preliminaries / CESMM Class A General Items are excluded.
A4: Ref | B4: Page | C4: Class | D4: Section | E4: Sub-heading | F4: Item | G4: Unit | H4: Gang hrs | I4: Labour £ | J4: Plant £ | K4: Material £ | L4: Sub-contract £ | M4: UK COST £ | N4: Labour € | O4: Plant € | P4: Material € | Q4: Sub-contract € | R4: IRISH COST € | S4: Derivation basis | T4: Confidence | U4: Published rate £ (superseded) | V4: Variance £ | W4: Flag | X4: Derivation note
A5: 124 | B5: IMG_0066 | C5: CLASS B: GROUND INVESTIGATION | D5: 01 TRIAL PITS AND TRENCHES | E5: Trial holes measured by number; Excavating trial hole; plan size 1.0 x 2.0 m; supports, backfilling | F5: ne 1.0 m deep | G5: nr | H5: 0.24 | I5: 32.5 | J5: 89.59 | K5: 0 | L5: 0 | M5: =ROUND(SUM(I5:L5),2) | N5: =ROUND(I5*'Irish Basis'!$C$6*'Irish Basis'!$C$5,2) | O5: =ROUND(J5*'Irish Basis'!$C$7*'Irish Basis'!$C$5,2) | P5: =ROUND(K5*'Irish Basis'!$C$8*'Irish Basis'!$C$5,2) | Q5: =ROUND(L5*'Irish Basis'!$C$12*'Irish Basis'!$C$5,2) | R5: =ROUND(SUM(N5:Q5),2) | S5: Stated build-up | T5: High | U5: 122.09 | V5: =IF(U5="","",ROUND(M5-U5,2)) | X5: Labour + plant + material as published; reconciles to the published rate.
A6: 125 | B6: IMG_0066 | C6: CLASS B: GROUND INVESTIGATION | D6: 01 TRIAL PITS AND TRENCHES | E6: Trial holes measured by number; Excavating trial hole; plan size 1.0 x 2.0 m; supports, backfilling | F6: 1.0-2.0 m deep | G6: nr | H6: 0.47 | I6: 63.64 | J6: 114.75 | K6: 0 | L6: 0 | M6: =ROUND(SUM(I6:L6),2) | N6: =ROUND(I6*'Irish Basis'!$C$6*'Irish Basis'!$C$5,2) | O6: =ROUND(J6*'Irish Basis'!$C$7*'Irish Basis'!$C$5,2) | P6: =ROUND(K6*'Irish Basis'!$C$8*'Irish Basis'!$C$5,2) | Q6: =ROUND(L6*'Irish Basis'!$C$12*'Irish Basis'!$C$5,2) | R6: =ROUND(SUM(N6:Q6),2) | S6: Stated build-up | T6: High | U6: 178.4 | V6: =IF(U6="","",ROUND(M6-U6,2)) | X6: Labour + plant + material as published; reconciles to the published rate.
A7: 126 | B7: IMG_0066 | C7: CLASS B: GROUND INVESTIGATION | D7: 01 TRIAL PITS AND TRENCHES | E7: Trial holes measured by number; Excavating trial hole; plan size 1.0 x 2.0 m; supports, backfilling | F7: over 2.0 m deep | G7: nr | H7: 0.53 | I7: 71.77 | J7: 140.11 | K7: 0 | L7: 0 | M7: =ROUND(SUM(I7:L7),2) | N7: =ROUND(I7*'Irish Basis'!$C$6*'Irish Basis'!$C$5,2) | O7: =ROUND(J7*'Irish Basis'!$C$7*'Irish Basis'!$C$5,2) | P7: =ROUND(K7*'Irish Basis'!$C$8*'Irish Basis'!$C$5,2) | Q7: =ROUND(L7*'Irish Basis'!$C$12*'Irish Basis'!$C$5,2) | R7: =ROUND(SUM(N7:Q7),2) | S7: Stated build-up | T7: High | U7: 211.88 | V7: =IF(U7="","",ROUND(M7-U7,2)) | X7: Labour + plant + material as published; reconciles to the published rate.
A8: 128 | B8: IMG_0066 | C8: CLASS B: GROUND INVESTIGATION | D8: 01 TRIAL PITS AND TRENCHES | E8: Trial holes measured by number; Excavating trial hole in rock or similar; plan size 1.0 x 2.0 m; supports, backfilling | F8: ne 1.0 m deep | G8: nr | H8: 0.28 | I8: 37.92 | J8: 96.41 | K8: 0 | L8: 0 | M8: =ROUND(SUM(I8:L8),2) | N8: =ROUND(I8*'Irish Basis'!$C$6*'Irish Basis'!$C$5,2) | O8: =ROUND(J8*'Irish Basis'!$C$7*'Irish Basis'!$C$5,2) | P8: =ROUND(K8*'Irish Basis'!$C$8*'Irish Basis'!$C$5,2) | Q8: =ROUND(L8*'Irish Basis'!$C$12*'Irish Basis'!$C$5,2) | R8: =ROUND(SUM(N8:Q8),2) | S8: Stated build-up | T8: High | U8: 134.33 | V8: =IF(U8="","",ROUND(M8-U8,2)) | X8: Labour + plant + material as published; reconciles to the published rate.
A9: 129 | B9: IMG_0066 | C9: CLASS B: GROUND INVESTIGATION | D9: 01 TRIAL PITS AND TRENCHES | E9: Trial holes measured by number; Excavating trial hole in rock or similar; plan size 1.0 x 2.0 m; supports, backfilling | F9: 1.0-2.0 m deep | G9: nr | H9: 0.51 | I9: 69.06 | J9: 137.6 | K9: 0 | L9: 0 | M9: =ROUND(SUM(I9:L9),2) | N9: =ROUND(I9*'Irish Basis'!$C$6*'Irish Basis'!$C$5,2) | O9: =ROUND(J9*'Irish Basis'!$C$7*'Irish Basis'!$C$5,2) | P9: =ROUND(K9*'Irish Basis'!$C$8*'Irish Basis'!$C$5,2) | Q9: =ROUND(L9*'Irish Basis'!$C$12*'Irish Basis'!$C$5,2) | R9: =ROUND(SUM(N9:Q9),2) | S9: Stated build-up | T9: High | U9: 206.66 | V9: =IF(U9="","",ROUND(M9-U9,2)) | X9: Labour + plant + material as published; reconciles to the published rate.
A10: 130 | B10: IMG_0066 | C10: CLASS B: GROUND INVESTIGATION | D10: 01 TRIAL PITS AND TRENCHES | E10: Trial holes measured by number; Excavating trial hole in rock or similar; plan size 1.0 x 2.0 m; supports, backfilling | F10: over 2.0 m deep | G10: nr | H10: 0.58 | I10: 78.54 | J10: 164.71 | K10: 0 | L10: 0 | M10: =ROUND(SUM(I10:L10),2) | N10: =ROUND(I10*'Irish Basis'!$C$6*'Irish Basis'!$C$5,2) | O10: =ROUND(J10*'Irish Basis'!$C$7*'Irish Basis'!$C$5,2) | P10: =ROUND(K10*'Irish Basis'!$C$8*'Irish Basis'!$C$5,2) | Q10: =ROUND(L10*'Irish Basis'!$C$12*'Irish Basis'!$C$5,2) | R10: =ROUND(SUM(N10:Q10),2) | S10: Stated build-up | T10: High | U10: 243.25 | V10: =IF(U10="","",ROUND(M10-U10,2)) | X10: Labour + plant + material as published; reconciles to the published rate.
A11: 132 | B11: IMG_0066 | C11: CLASS B: GROUND INVESTIGATION | D11: 01 TRIAL PITS AND TRENCHES | E11: Trial holes measured by depth; Excavating trial hole; plan size 1.0 x 2.0 m; supports, backfilling | F11: ne 1.0 m deep | G11: m | H11: 0.24 | I11: 32.5 | J11: 91.39 | K11: 0 | L11: 0 | M11: =ROUND(SUM(I11:L11),2) | N11: =ROUND(I11*'Irish Basis'!$C$6*'Irish Basis'!$C$5,2) | O11: =ROUND(J11*'Irish Basis'!$C$7*'Irish Basis'!$C$5,2) | P11: =ROUND(K11*'Irish Basis'!$C$8*'Irish Basis'!$C$5,2) | Q11: =ROUND(L11*'Irish Basis'!$C$12*'Irish Basis'!$C$5,2) | R11: =ROUND(SUM(N11:Q11),2) | S11: Stated build-up | T11: High | U11: 123.89 | V11: =IF(U11="","",ROUND(M11-U11,2)) | X11: Labour + plant + material as published; reconciles to the published rate.
A12: 134 | B12: IMG_0067 | C12: CLASS B: GROUND INVESTIGATION | D12: 01 TRIAL PITS AND TRENCHES | E12: Trial holes measured by depth; Excavating trial hole; plan size 1.0 x 2.0 m; supports, backfilling (continued) | F12: 1.0-2.0 m deep | G12: m | H12: 0.53 | I12: 71.77 | J12: 127.86 | K12: 0 | L12: 0 | M12: =ROUND(SUM(I12:L12),2) | N12: =ROUND(I12*'Irish Basis'!$C$6*'Irish Basis'!$C$5,2) | O12: =ROUND(J12*'Irish Basis'!$C$7*'Irish Basis'!$C$5,2) | P12: =ROUND(K12*'Irish Basis'!$C$8*'Irish Basis'!$C$5,2) | Q12: =ROUND(L12*'Irish Basis'!$C$12*'Irish Basis'!$C$5,2) | R12: =ROUND(SUM(N12:Q12),2) | S12: Stated build-up | T12: High | U12: 199.63 | V12: =IF(U12="","",ROUND(M12-U12,2)) | X12: Labour + plant + material as published; reconciles to the published rate.
A13: 135 | B13: IMG_0067 | C13: CLASS B: GROUND INVESTIGATION | D13: 01 TRIAL PITS AND TRENCHES | E13: Trial holes measured by depth; Excavating trial hole; plan size 1.0 x 2.0 m; supports, backfilling (continued) | F13: 2.0-3.0 m deep | G13: m | H13: 0.59 | I13: 79.89 | J13: 135.29 | K13: 0 | L13: 0 | M13: =ROUND(SUM(I13:L13),2) | N13: =ROUND(I13*'Irish Basis'!$C$6*'Irish Basis'!$C$5,2) | O13: =ROUND(J13*'Irish Basis'!$C$7*'Irish Basis'!$C$5,2) | P13: =ROUND(K13*'Irish Basis'!$C$8*'Irish Basis'!$C$5,2) | Q13: =ROUND(L13*'Irish Basis'!$C$12*'Irish Basis'!$C$5,2) | R13: =ROUND(SUM(N13:Q13),2) | S13: Stated build-up | T13: High | U13: 215.18 | V13: =IF(U13="","",ROUND(M13-U13,2)) | X13: Labour + plant + material as published; reconciles to the published rate.
A14: 136 | B14: IMG_0067 | C14: CLASS B: GROUND INVESTIGATION | D14: 01 TRIAL PITS AND TRENCHES | E14: Trial holes measured by depth; Excavating trial hole; plan size 1.0 x 2.0 m; supports, backfilling (continued) | F14: 3.0-5.0 m deep | G14: m | H14: 0.65 | I14: 88.02 | J14: 179.68 | K14: 0 | L14: 0 | M14: =ROUND(SUM(I14:L14),2) | N14: =ROUND(I14*'Irish Basis'!$C$6*'Irish Basis'!$C$5,2) | O14: =ROUND(J14*'Irish Basis'!$C$7*'Irish Basis'!$C$5,2) | P14: =ROUND(K14*'Irish Basis'!$C$8*'Irish Basis'!$C$5,2) | Q14: =ROUND(L14*'Irish Basis'!$C$12*'Irish Basis'!$C$5,2) | R14: =ROUND(SUM(N14:Q14),2) | S14: Stated build-up | T14: High | U14: 267.7 | V14: =IF(U14="","",ROUND(M14-U14,2)) | X14: Labour + plant + material as published; reconciles to the published rate.
A15: 138 | B15: IMG_0067 | C15: CLASS B: GROUND INVESTIGATION | D15: 01 TRIAL PITS AND TRENCHES | E15: Excavating trial hole in rock or similar; plan size 1.0 x 2.0 m; supports, backfilling | F15: ne 1.0 m deep | G15: m | H15: 2.95 | I15: 399.47 | J15: 615.51 | K15: 0 | L15: 0 | M15: =ROUND(SUM(I15:L15),2) | N15: =ROUND(I15*'Irish Basis'!$C$6*'Irish Basis'!$C$5,2) | O15: =ROUND(J15*'Irish Basis'!$C$7*'Irish Basis'!$C$5,2) | P15: =ROUND(K15*'Irish Basis'!$C$8*'Irish Basis'!$C$5,2) | Q15: =ROUND(L15*'Irish Basis'!$C$12*'Irish Basis'!$C$5,2) | R15: =ROUND(SUM(N15:Q15),2) | S15: Stated build-up | T15: High | U15: 1014.98 | V15: =IF(U15="","",ROUND(M15-U15,2)) | X15: Labour + plant + material as published; reconciles to the published rate.
A16: 139 | B16: IMG_0067 | C16: CLASS B: GROUND INVESTIGATION | D16: 01 TRIAL PITS AND TRENCHES | E16: Excavating trial hole in rock or similar; plan size 1.0 x 2.0 m; supports, backfilling | F16: 1.0-2.0 m deep | G16: m | H16: 3.65 | I16: 494.26 | J16: 948.3 | K16: 0 | L16: 0 | M16: =ROUND(SUM(I16:L16),2) | N16: =ROUND(I16*'Irish Basis'!$C$6*'Irish Basis'!$C$5,2) | O16: =ROUND(J16*'Irish Basis'!$C$7*'Irish Basis'!$C$5,2) | P16: =ROUND(K16*'Irish Basis'!$C$8*'Irish Basis'!$C$5,2) | Q16: =ROUND(L16*'Irish Basis'!$C$12*'Irish Basis'!$C$5,2) | R16: =ROUND(SUM(N16:Q16),2) | S16: Stated build-up | T16: High | U16: 1442.56 | V16: =IF(U16="","",ROUND(M16-U16,2)) | X16: Labour + plant + material as published; reconciles to the published rate.
... A20: 144 | B20: IMG_0067 | C20: CLASS B: GROUND INVESTIGATION | D20: 01 TRIAL PITS AND TRENCHES | E20: Sundries in trial holes | F20: Pumping; maximum depth 4.0 m minimum 750 litres per hour | G20: hr | H20: 0.06 | I20: 3.18 | J20: 38.03 | K20: 0 | L20: 0 | M20: =ROUND(SUM(I20:L20),2) | N20: =ROUND(I20*'Irish Basis'!$C$6*'Irish Basis'!$C$5,2) | O20: =ROUND(J20*'Irish Basis'!$C$7*'Irish Basis'!$C$5,2) | P20: =ROUND(K20*'Irish Basis'!$C$8*'Irish Basis'!$C$5,2) | Q20: =ROUND(L20*'Irish Basis'!$C$12*'Irish Basis'!$C$5,2) | R20: =ROUND(SUM(N20:Q20),2) | S20: Stated build-up | T20: High | U20: 41.21 | V20: =IF(U20="","",ROUND(M20-U20,2)) | X20: Labour + plant + material as published; reconciles to the published rate.
A21: 148 | B21: IMG_0067 | C21: CLASS B: GROUND INVESTIGATION | D21: 02 LIGHT CABLE PERCUSSION BOREHOLES | E21: General | F21: Establishment of standard plant and equipment and removal on completion | G21: item | I21: 0 | J21: 0 | K21: 0 | L21: 16858.03 | M21: =ROUND(SUM(I21:L21),2) | N21: =ROUND(I21*'Irish Basis'!$C$6*'Irish Basis'!$C$5,2) | O21: =ROUND(J21*'Irish Basis'!$C$7*'Irish Basis'!$C$5,2) | P21: =ROUND(K21*'Irish Basis'!$C$8*'Irish Basis'!$C$5,2) | Q21: =ROUND(L21*'Irish Basis'!$C$12*'Irish Basis'!$C$5,2) | R21: =ROUND(SUM(N21:Q21),2) | S21: All-in specialist rate | T21: All-in (not split) | U21: 16858.03 | V21: =IF(U21="","",ROUND(M21-U21,2)) | X21: Source publishes a specialist/sub-contract all-in rate; no labour/plant/material build-up exists to derive from.
A22: 149 | B22: IMG_0067 | C22: CLASS B: GROUND INVESTIGATION | D22: 02 LIGHT CABLE PERCUSSION BOREHOLES | E22: General | F22: Number; 150 mm nominal dia. at base | G22: nr | I22: 0 | J22: 0 | K22: 0 | L22: 87.91 | M22: =ROUND(SUM(I22:L22),2) | N22: =ROUND(I22*'Irish Basis'!$C$6*'Irish Basis'!$C$5,2) | O22: =ROUND(J22*'Irish Basis'!$C$7*'Irish Basis'!$C$5,2) | P22: =ROUND(K22*'Irish Basis'!$C$8*'Irish Basis'!$C$5,2) | Q22: =ROUND(L22*'Irish Basis'!$C$12*'Irish Basis'!$C$5,2) | R22: =ROUND(SUM(N22:Q22),2) | S22: All-in specialist rate | T22: All-in (not split) | U22: 87.91 | V22: =IF(U22="","",ROUND(M22-U22,2)) | X22: Source publishes a specialist/sub-contract all-in rate; no labour/plant/material build-up exists to derive from.
A23: 151 | B23: IMG_0067 | C23: CLASS B: GROUND INVESTIGATION | D23: 02 LIGHT CABLE PERCUSSION BOREHOLES | E23: Depth; 150 mm nominal dia. of base | F23: in holes of maximum depth not exceeding 5 m | G23: m | I23: 0 | J23: 0 | K23: 0 | L23: 35.16 | M23: =ROUND(SUM(I23:L23),2) | N23: =ROUND(I23*'Irish Basis'!$C$6*'Irish Basis'!$C$5,2) | O23: =ROUND(J23*'Irish Basis'!$C$7*'Irish Basis'!$C$5,2) | P23: =ROUND(K23*'Irish Basis'!$C$8*'Irish Basis'!$C$5,2) | Q23: =ROUND(L23*'Irish Basis'!$C$12*'Irish Basis'!$C$5,2) | R23: =ROUND(SUM(N23:Q23),2) | S23: All-in specialist rate | T23: All-in (not split) | U23: 35.16 | V23: =IF(U23="","",ROUND(M23-U23,2)) | X23: Source publishes a specialist/sub-contract all-in rate; no labour/plant/material build-up exists to derive from.
A24: 152 | B24: IMG_0067 | C24: CLASS B: GROUND INVESTIGATION | D24: 02 LIGHT CABLE PERCUSSION BOREHOLES | E24: Depth; 150 mm nominal dia. of base | F24: in holes of maximum depth 5-10 m | G24: m | I24: 0 | J24: 0 | K24: 0 | L24: 35.16 | M24: =ROUND(SUM(I24:L24),2) | N24: =ROUND(I24*'Irish Basis'!$C$6*'Irish Basis'!$C$5,2) | O24: =ROUND(J24*'Irish Basis'!$C$7*'Irish Basis'!$C$5,2) | P24: =ROUND(K24*'Irish Basis'!$C$8*'Irish Basis'!$C$5,2) | Q24: =ROUND(L24*'Irish Basis'!$C$12*'Irish Basis'!$C$5,2) | R24: =ROUND(SUM(N24:Q24),2) | S24: All-in specialist rate | T24: All-in (not split) | U24: 35.16 | V24: =IF(U24="","",ROUND(M24-U24,2)) | X24: Source publishes a specialist/sub-contract all-in rate; no labour/plant/material build-up exists to derive from.
A25: 153 | B25: IMG_0067 | C25: CLASS B: GROUND INVESTIGATION | D25: 02 LIGHT CABLE PERCUSSION BOREHOLES | E25: Depth; 150 mm nominal dia. of base | F25: in holes of maximum depth 10-20 m | G25: m | I25: 0 | J25: 0 | K25: 0 | L25: 43.95 | M25: =ROUND(SUM(I25:L25),2) | N25: =ROUND(I25*'Irish Basis'!$C$6*'Irish Basis'!$C$5,2) | O25: =ROUND(J25*'Irish Basis'!$C$7*'Irish Basis'!$C$5,2) | P25: =ROUND(K25*'Irish Basis'!$C$8*'Irish Basis'!$C$5,2) | Q25: =ROUND(L25*'Irish Basis'!$C$12*'Irish Basis'!$C$5,2) | R25: =ROUND(SUM(N25:Q25),2) | S25: All-in specialist rate | T25: All-in (not split) | U25: 43.95 | V25: =IF(U25="","",ROUND(M25-U25,2)) | X25: Source publishes a specialist/sub-contract all-in rate; no labour/plant/material build-up exists to derive from.
A26: 154 | B26: IMG_0067 | C26: CLASS B: GROUND INVESTIGATION | D26: 02 LIGHT CABLE PERCUSSION BOREHOLES | E26: Depth; 150 mm nominal dia. of base | F26: in holes of maximum depth 20-30 m | G26: m | I26: 0 | J26: 0 | K26: 0 | L26: 56.24 | M26: =ROUND(SUM(I26:L26),2) | N26: =ROUND(I26*'Irish Basis'!$C$6*'Irish Basis'!$C$5,2) | O26: =ROUND(J26*'Irish Basis'!$C$7*'Irish Basis'!$C$5,2) | P26: =ROUND(K26*'Irish Basis'!$C$8*'Irish Basis'!$C$5,2) | Q26: =ROUND(L26*'Irish Basis'!$C$12*'Irish Basis'!$C$5,2) | R26: =ROUND(SUM(N26:Q26),2) | S26: All-in specialist rate | T26: All-in (not split) | U26: 56.24 | V26: =IF(U26="","",ROUND(M26-U26,2)) | X26: Source publishes a specialist/sub-contract all-in rate; no labour/plant/material build-up exists to derive from.
A27: 155 | B27: IMG_0067 | C27: CLASS B: GROUND INVESTIGATION | D27: 02 LIGHT CABLE PERCUSSION BOREHOLES | E27: Depth; 150 mm nominal dia. of base | F27: Depth backfilled; imported pulverised fuel ash | G27: m | I27: 0 | J27: 0 | K27: 0 | L27: 9.1 | M27: =ROUND(SUM(I27:L27),2) | N27: =ROUND(I27*'Irish Basis'!$C$6*'Irish Basis'!$C$5,2) | O27: =ROUND(J27*'Irish Basis'!$C$7*'Irish Basis'!$C$5,2) | P27: =ROUND(K27*'Irish Basis'!$C$8*'Irish Basis'!$C$5,2) | Q27: =ROUND(L27*'Irish Basis'!$C$12*'Irish Basis'!$C$5,2) | R27: =ROUND(SUM(N27:Q27),2) | S27: All-in specialist rate | T27: All-in (not split) | U27: 9.1 | V27: =IF(U27="","",ROUND(M27-U27,2)) | X27: Source publishes a specialist/sub-contract all-in rate; no labour/plant/material build-up exists to derive from.
A28: 156 | B28: IMG_0067 | C28: CLASS B: GROUND INVESTIGATION | D28: 02 LIGHT CABLE PERCUSSION BOREHOLES | E28: Depth; 150 mm nominal dia. of base | F28: Depth backfilled; imported gravel | G28: m | I28: 0 | J28: 0 | K28: 0 | L28: 12.73 | M28: =ROUND(SUM(I28:L28),2) | N28: =ROUND(I28*'Irish Basis'!$C$6*'Irish Basis'!$C$5,2) | O28: =ROUND(J28*'Irish Basis'!$C$7*'Irish Basis'!$C$5,2) | P28: =ROUND(K28*'Irish Basis'!$C$8*'Irish Basis'!$C$5,2) | Q28: =ROUND(L28*'Irish Basis'!$C$12*'Irish Basis'!$C$5,2) | R28: =ROUND(SUM(N28:Q28),2) | S28: All-in specialist rate | T28: All-in (not split) | U28: 12.73 | V28: =IF(U28="","",ROUND(M28-U28,2)) | X28: Source publishes a specialist/sub-contract all-in rate; no labour/plant/material build-up exists to derive from.
A29: 157 | B29: IMG_0067 | C29: CLASS B: GROUND INVESTIGATION | D29: 02 LIGHT CABLE PERCUSSION BOREHOLES | E29: Depth; 150 mm nominal dia. of base | F29: Depth backfilled; bentonite grout | G29: m | I29: 0 | J29: 0 | K29: 0 | L29: 18.21 | M29: =ROUND(SUM(I29:L29),2) | N29: =ROUND(I29*'Irish Basis'!$C$6*'Irish Basis'!$C$5,2) | O29: =ROUND(J29*'Irish Basis'!$C$7*'Irish Basis'!$C$5,2) | P29: =ROUND(K29*'Irish Basis'!$C$8*'Irish Basis'!$C$5,2) | Q29: =ROUND(L29*'Irish Basis'!$C$12*'Irish Basis'!$C$5,2) | R29: =ROUND(SUM(N29:Q29),2) | S29: All-in specialist rate | T29: All-in (not split) | U29: 18.21 | V29: =IF(U29="","",ROUND(M29-U29,2)) | X29: Source publishes a specialist/sub-contract all-in rate; no labour/plant/material build-up exists to derive from.
A30: 158 | B30: IMG_0067 | C30: CLASS B: GROUND INVESTIGATION | D30: 02 LIGHT CABLE PERCUSSION BOREHOLES | E30: Depth; 150 mm nominal dia. of base | F30: Chiselling to prove rock or to penetrate obstructions | G30: hour | I30: 0 | J30: 0 | K30: 0 | L30: 87.93 | M30: =ROUND(SUM(I30:L30),2) | N30: =ROUND(I30*'Irish Basis'!$C$6*'Irish Basis'!$C$5,2) | O30: =ROUND(J30*'Irish Basis'!$C$7*'Irish Basis'!$C$5,2) | P30: =ROUND(K30*'Irish Basis'!$C$8*'Irish Basis'!$C$5,2) | Q30: =ROUND(L30*'Irish Basis'!$C$12*'Irish Basis'!$C$5,2) | R30: =ROUND(SUM(N30:Q30),2) | S30: All-in specialist rate | T30: All-in (not split) | U30: 87.93 | V30: =IF(U30="","",ROUND(M30-U30,2)) | X30: Source publishes a specialist/sub-contract all-in rate; no labour/plant/material build-up exists to derive from.
A31: 159 | B31: IMG_0067 | C31: CLASS B: GROUND INVESTIGATION | D31: 02 LIGHT CABLE PERCUSSION BOREHOLES | E31: Depth; 150 mm nominal dia. of base | F31: Standing time of rig and crew | G31: hour | I31: 0 | J31: 0 | K31: 0 | L31: 87.93 | M31: =ROUND(SUM(I31:L31),2) | N31: =ROUND(I31*'Irish Basis'!$C$6*'Irish Basis'!$C$5,2) | O31: =ROUND(J31*'Irish Basis'!$C$7*'Irish Basis'!$C$5,2) | P31: =ROUND(K31*'Irish Basis'!$C$8*'Irish Basis'!$C$5,2) | Q31: =ROUND(L31*'Irish Basis'!$C$12*'Irish Basis'!$C$5,2) | R31: =ROUND(SUM(N31:Q31),2) | S31: All-in specialist rate | T31: All-in (not split) | U31: 87.93 | V31: =IF(U31="","",ROUND(M31-U31,2)) | X31: Source publishes a specialist/sub-contract all-in rate; no labour/plant/material build-up exists to derive from.
A32: 162 | B32: IMG_0067 | C32: CLASS B: GROUND INVESTIGATION | D32: 03 ROTARY DRILLED BOREHOLES | F32: Establishment of standard plant and equipment and removal on completion | G32: item | I32: 0 | J32: 0 | K32: 0 | L32: 42145.07 | M32: =ROUND(SUM(I32:L32),2) | N32: =ROUND(I32*'Irish Basis'!$C$6*'Irish Basis'!$C$5,2) | O32: =ROUND(J32*'Irish Basis'!$C$7*'Irish Basis'!$C$5,2) | P32: =ROUND(K32*'Irish Basis'!$C$8*'Irish Basis'!$C$5,2) | Q32: =ROUND(L32*'Irish Basis'!$C$12*'Irish Basis'!$C$5,2) | R32: =ROUND(SUM(N32:Q32),2) | S32: All-in specialist rate | T32: All-in (not split) | U32: 42145.07 | V32: =IF(U32="","",ROUND(M32-U32,2)) | X32: Source publishes a specialist/sub-contract all-in rate; no labour/plant/material build-up exists to derive from.
A33: 163 | B33: IMG_0067 | C33: CLASS B: GROUND INVESTIGATION | D33: 03 ROTARY DRILLED BOREHOLES | F33: Setting up at each borehole position | G33: nr | I33: 0 | J33: 0 | K33: 0 | L33: 17.58 | M33: =ROUND(SUM(I33:L33),2) | N33: =ROUND(I33*'Irish Basis'!$C$6*'Irish Basis'!$C$5,2) | O33: =ROUND(J33*'Irish Basis'!$C$7*'Irish Basis'!$C$5,2) | P33: =ROUND(K33*'Irish Basis'!$C$8*'Irish Basis'!$C$5,2) | Q33: =ROUND(L33*'Irish Basis'!$C$12*'Irish Basis'!$C$5,2) | R33: =ROUND(SUM(N33:Q33),2) | S33: All-in specialist rate | T33: All-in (not split) | U33: 17.58 | V33: =IF(U33="","",ROUND(M33-U33,2)) | X33: Source publishes a specialist/sub-contract all-in rate; no labour/plant/material build-up exists to derive from.
A34: 165 | B34: IMG_0067 | C34: CLASS B: GROUND INVESTIGATION | D34: 03 ROTARY DRILLED BOREHOLES | E34: Depth without core recovery; nominal minimum core dia. 100 mm | F34: ne 5.0 m deep | G34: m | I34: 0 | J34: 0 | K34: 0 | L34: 99.82 | M34: =ROUND(SUM(I34:L34),2) | N34: =ROUND(I34*'Irish Basis'!$C$6*'Irish Basis'!$C$5,2) | O34: =ROUND(J34*'Irish Basis'!$C$7*'Irish Basis'!$C$5,2) | P34: =ROUND(K34*'Irish Basis'!$C$8*'Irish Basis'!$C$5,2) | Q34: =ROUND(L34*'Irish Basis'!$C$12*'Irish Basis'!$C$5,2) | R34: =ROUND(SUM(N34:Q34),2) | S34: All-in specialist rate | T34: All-in (not split) | U34: 99.82 | V34: =IF(U34="","",ROUND(M34-U34,2)) | X34: Source publishes a specialist/sub-contract all-in rate; no labour/plant/material build-up exists to derive from.
A35: 166 | B35: IMG_0067 | C35: CLASS B: GROUND INVESTIGATION | D35: 03 ROTARY DRILLED BOREHOLES | E35: Depth without core recovery; nominal minimum core dia. 100 mm | F35: 5-10 m deep | G35: m | I35: 0 | J35: 0 | K35: 0 | L35: 99.82 | M35: =ROUND(SUM(I35:L35),2) | N35: =ROUND(I35*'Irish Basis'!$C$6*'Irish Basis'!$C$5,2) | O35: =ROUND(J35*'Irish Basis'!$C$7*'Irish Basis'!$C$5,2) | P35: =ROUND(K35*'Irish Basis'!$C$8*'Irish Basis'!$C$5,2) | Q35: =ROUND(L35*'Irish Basis'!$C$12*'Irish Basis'!$C$5,2) | R35: =ROUND(SUM(N35:Q35),2) | S35: All-in specialist rate | T35: All-in (not split) | U35: 99.82 | V35: =IF(U35="","",ROUND(M35-U35,2)) | X35: Source publishes a specialist/sub-contract all-in rate; no labour/plant/material build-up exists to derive from.
A36: 167 | B36: IMG_0067 | C36: CLASS B: GROUND INVESTIGATION | D36: 03 ROTARY DRILLED BOREHOLES | E36: Depth without core recovery; nominal minimum core dia. 100 mm | F36: 10-20 m deep | G36: m | I36: 0 | J36: 0 | K36: 0 | L36: 110.47 | M36: =ROUND(SUM(I36:L36),2) | N36: =ROUND(I36*'Irish Basis'!$C$6*'Irish Basis'!$C$5,2) | O36: =ROUND(J36*'Irish Basis'!$C$7*'Irish Basis'!$C$5,2) | P36: =ROUND(K36*'Irish Basis'!$C$8*'Irish Basis'!$C$5,2) | Q36: =ROUND(L36*'Irish Basis'!$C$12*'Irish Basis'!$C$5,2) | R36: =ROUND(SUM(N36:Q36),2) | S36: All-in specialist rate | T36: All-in (not split) | U36: 110.47 | V36: =IF(U36="","",ROUND(M36-U36,2)) | X36: Source publishes a specialist/sub-contract all-in rate; no labour/plant/material build-up exists to derive from.
A37: 168 | B37: IMG_0067 | C37: CLASS B: GROUND INVESTIGATION | D37: 03 ROTARY DRILLED BOREHOLES | E37: Depth without core recovery; nominal minimum core dia. 100 mm | F37: 20-30 m deep | G37: m | I37: 0 | J37: 0 | K37: 0 | L37: 110.47 | M37: =ROUND(SUM(I37:L37),2) | N37: =ROUND(I37*'Irish Basis'!$C$6*'Irish Basis'!$C$5,2) | O37: =ROUND(J37*'Irish Basis'!$C$7*'Irish Basis'!$C$5,2) | P37: =ROUND(K37*'Irish Basis'!$C$8*'Irish Basis'!$C$5,2) | Q37: =ROUND(L37*'Irish Basis'!$C$12*'Irish Basis'!$C$5,2) | R37: =ROUND(SUM(N37:Q37),2) | S37: All-in specialist rate | T37: All-in (not split) | U37: 110.47 | V37: =IF(U37="","",ROUND(M37-U37,2)) | X37: Source publishes a specialist/sub-contract all-in rate; no labour/plant/material build-up exists to derive from.
A38: 170 | B38: IMG_0067 | C38: CLASS B: GROUND INVESTIGATION | D38: 03 ROTARY DRILLED BOREHOLES | E38: Depth with core recovery; nominal minimum core dia. 75 mm | F38: ne 5.0 m deep | G38: m | I38: 0 | J38: 0 | K38: 0 | L38: 163.71 | M38: =ROUND(SUM(I38:L38),2) | N38: =ROUND(I38*'Irish Basis'!$C$6*'Irish Basis'!$C$5,2) | O38: =ROUND(J38*'Irish Basis'!$C$7*'Irish Basis'!$C$5,2) | P38: =ROUND(K38*'Irish Basis'!$C$8*'Irish Basis'!$C$5,2) | Q38: =ROUND(L38*'Irish Basis'!$C$12*'Irish Basis'!$C$5,2) | R38: =ROUND(SUM(N38:Q38),2) | S38: All-in specialist rate | T38: All-in (not split) | U38: 163.71 | V38: =IF(U38="","",ROUND(M38-U38,2)) | X38: Source publishes a specialist/sub-contract all-in rate; no labour/plant/material build-up exists to derive from.
A39: 171 | B39: IMG_0067 | C39: CLASS B: GROUND INVESTIGATION | D39: 03 ROTARY DRILLED BOREHOLES | E39: Depth with core recovery; nominal minimum core dia. 75 mm | F39: 5-10 m deep | G39: m | I39: 0 | J39: 0 | K39: 0 | L39: 165.04 | M39: =ROUND(SUM(I39:L39),2) | N39: =ROUND(I39*'Irish Basis'!$C$6*'Irish Basis'!$C$5,2) | O39: =ROUND(J39*'Irish Basis'!$C$7*'Irish Basis'!$C$5,2) | P39: =ROUND(K39*'Irish Basis'!$C$8*'Irish Basis'!$C$5,2) | Q39: =ROUND(L39*'Irish Basis'!$C$12*'Irish Basis'!$C$5,2) | R39: =ROUND(SUM(N39:Q39),2) | S39: All-in specialist rate | T39: All-in (not split) | U39: 165.04 | V39: =IF(U39="","",ROUND(M39-U39,2)) | X39: Source publishes a specialist/sub-contract all-in rate; no labour/plant/material build-up exists to derive from.
A40: 172 | B40: IMG_0067 | C40: CLASS B: GROUND INVESTIGATION | D40: 03 ROTARY DRILLED BOREHOLES | E40: Depth with core recovery; nominal minimum core dia. 75 mm | F40: 10-20 m deep | G40: m | I40: 0 | J40: 0 | K40: 0 | L40: 192.99 | M40: =ROUND(SUM(I40:L40),2) | N40: =ROUND(I40*'Irish Basis'!$C$6*'Irish Basis'!$C$5,2) | O40: =ROUND(J40*'Irish Basis'!$C$7*'Irish Basis'!$C$5,2) | P40: =ROUND(K40*'Irish Basis'!$C$8*'Irish Basis'!$C$5,2) | Q40: =ROUND(L40*'Irish Basis'!$C$12*'Irish Basis'!$C$5,2) | R40: =ROUND(SUM(N40:Q40),2) | S40: All-in specialist rate | T40: All-in (not split) | U40: 192.99 | V40: =IF(U40="","",ROUND(M40-U40,2)) | X40: Source publishes a specialist/sub-contract all-in rate; no labour/plant/material build-up exists to derive from.
A41: 173 | B41: IMG_0067 | C41: CLASS B: GROUND INVESTIGATION | D41: 03 ROTARY DRILLED BOREHOLES | E41: Depth with core recovery; nominal minimum core dia. 75 mm | F41: 20-30 m deep | G41: m | I41: 0 | J41: 0 | K41: 0 | L41: 263.53 | M41: =ROUND(SUM(I41:L41),2) | N41: =ROUND(I41*'Irish Basis'!$C$6*'Irish Basis'!$C$5,2) | O41: =ROUND(J41*'Irish Basis'!$C$7*'Irish Basis'!$C$5,2) | P41: =ROUND(K41*'Irish Basis'!$C$8*'Irish Basis'!$C$5,2) | Q41: =ROUND(L41*'Irish Basis'!$C$12*'Irish Basis'!$C$5,2) | R41: =ROUND(SUM(N41:Q41),2) | S41: All-in specialist rate | T41: All-in (not split) | U41: 263.53 | V41: =IF(U41="","",ROUND(M41-U41,2)) | X41: Source publishes a specialist/sub-contract all-in rate; no labour/plant/material build-up exists to derive from.
A42: 174 | B42: IMG_0067 | C42: CLASS B: GROUND INVESTIGATION | D42: 03 ROTARY DRILLED BOREHOLES | E42: Depth with core recovery; nominal minimum core dia. 75 mm | F42: Depth cased; semi-rigid plastic core barrel liner | G42: m | I42: 0 | J42: 0 | K42: 0 | L42: 15.97 | M42: =ROUND(SUM(I42:L42),2) | N42: =ROUND(I42*'Irish Basis'!$C$6*'Irish Basis'!$C$5,2) | O42: =ROUND(J42*'Irish Basis'!$C$7*'Irish Basis'!$C$5,2) | P42: =ROUND(K42*'Irish Basis'!$C$8*'Irish Basis'!$C$5,2) | Q42: =ROUND(L42*'Irish Basis'!$C$12*'Irish Basis'!$C$5,2) | R42: =ROUND(SUM(N42:Q42),2) | S42: All-in specialist rate | T42: All-in (not split) | U42: 15.97 | V42: =IF(U42="","",ROUND(M42-U42,2)) | X42: Source publishes a specialist/sub-contract all-in rate; no labour/plant/material build-up exists to derive from.
A43: 177 | B43: IMG_0067 | C43: CLASS B: GROUND INVESTIGATION | D43: 04 SAMPLES | E43: General; From the surface or from trial pits and trenches | F43: undisturbed soft material; minimum 200 mm cube | G43: nr | I43: 0 | J43: 0 | K43: 0 | L43: 28.59 | M43: =ROUND(SUM(I43:L43),2) | N43: =ROUND(I43*'Irish Basis'!$C$6*'Irish Basis'!$C$5,2) | O43: =ROUND(J43*'Irish Basis'!$C$7*'Irish Basis'!$C$5,2) | P43: =ROUND(K43*'Irish Basis'!$C$8*'Irish Basis'!$C$5,2) | Q43: =ROUND(L43*'Irish Basis'!$C$12*'Irish Basis'!$C$5,2) | R43: =ROUND(SUM(N43:Q43),2) | S43: All-in specialist rate | T43: All-in (not split) | U43: 28.59 | V43: =IF(U43="","",ROUND(M43-U43,2)) | X43: Source publishes a specialist/sub-contract all-in rate; no labour/plant/material build-up exists to derive from.
A44: 178 | B44: IMG_0067 | C44: CLASS B: GROUND INVESTIGATION | D44: 04 SAMPLES | E44: General; From the surface or from trial pits and trenches | F44: disturbed soft material; minimum 5 kg | G44: nr | I44: 0 | J44: 0 | K44: 0 | L44: 4.48 | M44: =ROUND(SUM(I44:L44),2) | N44: =ROUND(I44*'Irish Basis'!$C$6*'Irish Basis'!$C$5,2) | O44: =ROUND(J44*'Irish Basis'!$C$7*'Irish Basis'!$C$5,2) | P44: =ROUND(K44*'Irish Basis'!$C$8*'Irish Basis'!$C$5,2) | Q44: =ROUND(L44*'Irish Basis'!$C$12*'Irish Basis'!$C$5,2) | R44: =ROUND(SUM(N44:Q44),2) | S44: All-in specialist rate | T44: All-in (not split) | U44: 4.48 | V44: =IF(U44="","",ROUND(M44-U44,2)) | X44: Source publishes a specialist/sub-contract all-in rate; no labour/plant/material build-up exists to derive from.
A45: 179 | B45: IMG_0067 | C45: CLASS B: GROUND INVESTIGATION | D45: 04 SAMPLES | E45: General; From the surface or from trial pits and trenches | F45: rock; minimum 5 kg | G45: nr | I45: 0 | J45: 0 | K45: 0 | L45: 17.83 | M45: =ROUND(SUM(I45:L45),2) | N45: =ROUND(I45*'Irish Basis'!$C$6*'Irish Basis'!$C$5,2) | O45: =ROUND(J45*'Irish Basis'!$C$7*'Irish Basis'!$C$5,2) | P45: =ROUND(K45*'Irish Basis'!$C$8*'Irish Basis'!$C$5,2) | Q45: =ROUND(L45*'Irish Basis'!$C$12*'Irish Basis'!$C$5,2) | R45: =ROUND(SUM(N45:Q45),2) | S45: All-in specialist rate | T45: All-in (not split) | U45: 17.83 | V45: =IF(U45="","",ROUND(M45-U45,2)) | X45: Source publishes a specialist/sub-contract all-in rate; no labour/plant/material build-up exists to derive from.
... A91: 240 | B91: IMG_0068 | C91: CLASS B: GROUND INVESTIGATION | D91: 08 PROFESSIONAL SERVICES | E91: Visits to the Site | F91: principal or consultant | G91: nr | I91: 0 | J91: 0 | K91: 0 | L91: 151.92 | M91: =ROUND(SUM(I91:L91),2) | N91: =ROUND(I91*'Irish Basis'!$C$6*'Irish Basis'!$C$5,2) | O91: =ROUND(J91*'Irish Basis'!$C$7*'Irish Basis'!$C$5,2) | P91: =ROUND(K91*'Irish Basis'!$C$8*'Irish Basis'!$C$5,2) | Q91: =ROUND(L91*'Irish Basis'!$C$12*'Irish Basis'!$C$5,2) | R91: =ROUND(SUM(N91:Q91),2) | S91: All-in specialist rate | T91: All-in (not split) | U91: 151.92 | V91: =IF(U91="","",ROUND(M91-U91,2)) | X91: Source publishes a specialist/sub-contract all-in rate; no labour/plant/material build-up exists to derive from.
A92: 245 | B92: IMG_0068 | C92: CLASS C: GEOTECHNICAL AND OTHER SPECIALIST PROCESSES | D92: 01 DRILLING FOR GROUT HOLES | F92: Establishment of standard drilling plant and equipment and removal on completion | G92: item | I92: 0 | J92: 0 | K92: 0 | L92: 16128.32 | M92: =ROUND(SUM(I92:L92),2) | N92: =ROUND(I92*'Irish Basis'!$C$6*'Irish Basis'!$C$5,2) | O92: =ROUND(J92*'Irish Basis'!$C$7*'Irish Basis'!$C$5,2) | P92: =ROUND(K92*'Irish Basis'!$C$8*'Irish Basis'!$C$5,2) | Q92: =ROUND(L92*'Irish Basis'!$C$12*'Irish Basis'!$C$5,2) | R92: =ROUND(SUM(N92:Q92),2) | S92: All-in specialist rate | T92: All-in (not split) | U92: 16128.32 | V92: =IF(U92="","",ROUND(M92-U92,2)) | X92: Source publishes a specialist/sub-contract all-in rate; no labour/plant/material build-up exists to derive from.
A93: 246 | B93: IMG_0068 | C93: CLASS C: GEOTECHNICAL AND OTHER SPECIALIST PROCESSES | D93: 01 DRILLING FOR GROUT HOLES | F93: Rate per hole | G93: nr | I93: 0 | J93: 0 | K93: 0 | L93: 161.28 | M93: =ROUND(SUM(I93:L93),2) | N93: =ROUND(I93*'Irish Basis'!$C$6*'Irish Basis'!$C$5,2) | O93: =ROUND(J93*'Irish Basis'!$C$7*'Irish Basis'!$C$5,2) | P93: =ROUND(K93*'Irish Basis'!$C$8*'Irish Basis'!$C$5,2) | Q93: =ROUND(L93*'Irish Basis'!$C$12*'Irish Basis'!$C$5,2) | R93: =ROUND(SUM(N93:Q93),2) | S93: All-in specialist rate | T93: All-in (not split) | U93: 161.28 | V93: =IF(U93="","",ROUND(M93-U93,2)) | X93: Source publishes a specialist/sub-contract all-in rate; no labour/plant/material build-up exists to derive from.
A94: 247 | B94: IMG_0068 | C94: CLASS C: GEOTECHNICAL AND OTHER SPECIALIST PROCESSES | D94: 01 DRILLING FOR GROUT HOLES | F94: Standing time | G94: hour | I94: 0 | J94: 0 | K94: 0 | L94: 351.73 | M94: =ROUND(SUM(I94:L94),2) | N94: =ROUND(I94*'Irish Basis'!$C$6*'Irish Basis'!$C$5,2) | O94: =ROUND(J94*'Irish Basis'!$C$7*'Irish Basis'!$C$5,2) | P94: =ROUND(K94*'Irish Basis'!$C$8*'Irish Basis'!$C$5,2) | Q94: =ROUND(L94*'Irish Basis'!$C$12*'Irish Basis'!$C$5,2) | R94: =ROUND(SUM(N94:Q94),2) | S94: All-in specialist rate | T94: All-in (not split) | U94: 351.73 | V94: =IF(U94="","",ROUND(M94-U94,2)) | X94: Source publishes a specialist/sub-contract all-in rate; no labour/plant/material build-up exists to derive from.
A95: 248 | B95: IMG_0068 | C95: CLASS C: GEOTECHNICAL AND OTHER SPECIALIST PROCESSES | D95: 01 DRILLING FOR GROUT HOLES | F95: Multiple water pressure tests | G95: nr | I95: 0 | J95: 0 | K95: 0 | L95: 10.76 | M95: =ROUND(SUM(I95:L95),2) | N95: =ROUND(I95*'Irish Basis'!$C$6*'Irish Basis'!$C$5,2) | O95: =ROUND(J95*'Irish Basis'!$C$7*'Irish Basis'!$C$5,2) | P95: =ROUND(K95*'Irish Basis'!$C$8*'Irish Basis'!$C$5,2) | Q95: =ROUND(L95*'Irish Basis'!$C$12*'Irish Basis'!$C$5,2) | R95: =ROUND(SUM(N95:Q95),2) | S95: All-in specialist rate | T95: All-in (not split) | U95: 10.76 | V95: =IF(U95="","",ROUND(M95-U95,2)) | X95: Source publishes a specialist/sub-contract all-in rate; no labour/plant/material build-up exists to derive from.
A96: 250 | B96: IMG_0068 | C96: CLASS C: GEOTECHNICAL AND OTHER SPECIALIST PROCESSES | D96: 01 DRILLING FOR GROUT HOLES | E96: Drilling through material other than rock or artificial hard material; vertically downwards | F96: depth ne 5 m | G96: m | I96: 0 | J96: 0 | K96: 0 | L96: 30.76 | M96: =ROUND(SUM(I96:L96),2) | N96: =ROUND(I96*'Irish Basis'!$C$6*'Irish Basis'!$C$5,2) | O96: =ROUND(J96*'Irish Basis'!$C$7*'Irish Basis'!$C$5,2) | P96: =ROUND(K96*'Irish Basis'!$C$8*'Irish Basis'!$C$5,2) | Q96: =ROUND(L96*'Irish Basis'!$C$12*'Irish Basis'!$C$5,2) | R96: =ROUND(SUM(N96:Q96),2) | S96: All-in specialist rate | T96: All-in (not split) | U96: 30.76 | V96: =IF(U96="","",ROUND(M96-U96,2)) | X96: Source publishes a specialist/sub-contract all-in rate; no labour/plant/material build-up exists to derive from.
A97: 251 | B97: IMG_0068 | C97: CLASS C: GEOTECHNICAL AND OTHER SPECIALIST PROCESSES | D97: 01 DRILLING FOR GROUT HOLES | E97: Drilling through material other than rock or artificial hard material; vertically downwards | F97: depth 5-10 m | G97: m | I97: 0 | J97: 0 | K97: 0 | L97: 35.61 | M97: =ROUND(SUM(I97:L97),2) | N97: =ROUND(I97*'Irish Basis'!$C$6*'Irish Basis'!$C$5,2) | O97: =ROUND(J97*'Irish Basis'!$C$7*'Irish Basis'!$C$5,2) | P97: =ROUND(K97*'Irish Basis'!$C$8*'Irish Basis'!$C$5,2) | Q97: =ROUND(L97*'Irish Basis'!$C$12*'Irish Basis'!$C$5,2) | R97: =ROUND(SUM(N97:Q97),2) | S97: All-in specialist rate | T97: All-in (not split) | U97: 35.61 | V97: =IF(U97="","",ROUND(M97-U97,2)) | X97: Source publishes a specialist/sub-contract all-in rate; no labour/plant/material build-up exists to derive from.
A98: 252 | B98: IMG_0068 | C98: CLASS C: GEOTECHNICAL AND OTHER SPECIALIST PROCESSES | D98: 01 DRILLING FOR GROUT HOLES | E98: Drilling through material other than rock or artificial hard material; vertically downwards | F98: depth 10-20 m | G98: m | I98: 0 | J98: 0 | K98: 0 | L98: 42.19 | M98: =ROUND(SUM(I98:L98),2) | N98: =ROUND(I98*'Irish Basis'!$C$6*'Irish Basis'!$C$5,2) | O98: =ROUND(J98*'Irish Basis'!$C$7*'Irish Basis'!$C$5,2) | P98: =ROUND(K98*'Irish Basis'!$C$8*'Irish Basis'!$C$5,2) | Q98: =ROUND(L98*'Irish Basis'!$C$12*'Irish Basis'!$C$5,2) | R98: =ROUND(SUM(N98:Q98),2) | S98: All-in specialist rate | T98: All-in (not split) | U98: 42.19 | V98: =IF(U98="","",ROUND(M98-U98,2)) | X98: Source publishes a specialist/sub-contract all-in rate; no labour/plant/material build-up exists to derive from.
A99: 253 | B99: IMG_0068 | C99: CLASS C: GEOTECHNICAL AND OTHER SPECIALIST PROCESSES | D99: 01 DRILLING FOR GROUT HOLES | E99: Drilling through material other than rock or artificial hard material; vertically downwards | F99: depth 20-30 m | G99: m | I99: 0 | J99: 0 | K99: 0 | L99: 51.61 | M99: =ROUND(SUM(I99:L99),2) | N99: =ROUND(I99*'Irish Basis'!$C$6*'Irish Basis'!$C$5,2) | O99: =ROUND(J99*'Irish Basis'!$C$7*'Irish Basis'!$C$5,2) | P99: =ROUND(K99*'Irish Basis'!$C$8*'Irish Basis'!$C$5,2) | Q99: =ROUND(L99*'Irish Basis'!$C$12*'Irish Basis'!$C$5,2) | R99: =ROUND(SUM(N99:Q99),2) | S99: All-in specialist rate | T99: All-in (not split) | U99: 51.61 | V99: =IF(U99="","",ROUND(M99-U99,2)) | X99: Source publishes a specialist/sub-contract all-in rate; no labour/plant/material build-up exists to derive from.
A100: 255 | B100: IMG_0068 | C100: CLASS C: GEOTECHNICAL AND OTHER SPECIALIST PROCESSES | D100: 01 DRILLING FOR GROUT HOLES | E100: Downwards at an angle 0-45 deg to the vertical | F100: depth ne 5 m | G100: m | I100: 0 | J100: 0 | K100: 0 | L100: 30.76 | M100: =ROUND(SUM(I100:L100),2) | N100: =ROUND(I100*'Irish Basis'!$C$6*'Irish Basis'!$C$5,2) | O100: =ROUND(J100*'Irish Basis'!$C$7*'Irish Basis'!$C$5,2) | P100: =ROUND(K100*'Irish Basis'!$C$8*'Irish Basis'!$C$5,2) | Q100: =ROUND(L100*'Irish Basis'!$C$12*'Irish Basis'!$C$5,2) | R100: =ROUND(SUM(N100:Q100),2) | S100: All-in specialist rate | T100: All-in (not split) | U100: 30.76 | V100: =IF(U100="","",ROUND(M100-U100,2)) | X100: Source publishes a specialist/sub-contract all-in rate; no labour/plant/material build-up exists to derive from.
A101: 256 | B101: IMG_0068 | C101: CLASS C: GEOTECHNICAL AND OTHER SPECIALIST PROCESSES | D101: 01 DRILLING FOR GROUT HOLES | E101: Downwards at an angle 0-45 deg to the vertical | F101: depth 5-10 m | G101: m | I101: 0 | J101: 0 | K101: 0 | L101: 35.61 | M101: =ROUND(SUM(I101:L101),2) | N101: =ROUND(I101*'Irish Basis'!$C$6*'Irish Basis'!$C$5,2) | O101: =ROUND(J101*'Irish Basis'!$C$7*'Irish Basis'!$C$5,2) | P101: =ROUND(K101*'Irish Basis'!$C$8*'Irish Basis'!$C$5,2) | Q101: =ROUND(L101*'Irish Basis'!$C$12*'Irish Basis'!$C$5,2) | R101: =ROUND(SUM(N101:Q101),2) | S101: All-in specialist rate | T101: All-in (not split) | U101: 35.61 | V101: =IF(U101="","",ROUND(M101-U101,2)) | X101: Source publishes a specialist/sub-contract all-in rate; no labour/plant/material build-up exists to derive from.
A102: 257 | B102: IMG_0068 | C102: CLASS C: GEOTECHNICAL AND OTHER SPECIALIST PROCESSES | D102: 01 DRILLING FOR GROUT HOLES | E102: Downwards at an angle 0-45 deg to the vertical | F102: depth 10-20 m | G102: m | I102: 0 | J102: 0 | K102: 0 | L102: 42.19 | M102: =ROUND(SUM(I102:L102),2) | N102: =ROUND(I102*'Irish Basis'!$C$6*'Irish Basis'!$C$5,2) | O102: =ROUND(J102*'Irish Basis'!$C$7*'Irish Basis'!$C$5,2) | P102: =ROUND(K102*'Irish Basis'!$C$8*'Irish Basis'!$C$5,2) | Q102: =ROUND(L102*'Irish Basis'!$C$12*'Irish Basis'!$C$5,2) | R102: =ROUND(SUM(N102:Q102),2) | S102: All-in specialist rate | T102: All-in (not split) | U102: 42.19 | V102: =IF(U102="","",ROUND(M102-U102,2)) | X102: Source publishes a specialist/sub-contract all-in rate; no labour/plant/material build-up exists to derive from.
A103: 258 | B103: IMG_0068 | C103: CLASS C: GEOTECHNICAL AND OTHER SPECIALIST PROCESSES | D103: 01 DRILLING FOR GROUT HOLES | E103: Downwards at an angle 0-45 deg to the vertical | F103: depth 20-30 m | G103: m | I103: 0 | J103: 0 | K103: 0 | L103: 51.61 | M103: =ROUND(SUM(I103:L103),2) | N103: =ROUND(I103*'Irish Basis'!$C$6*'Irish Basis'!$C$5,2) | O103: =ROUND(J103*'Irish Basis'!$C$7*'Irish Basis'!$C$5,2) | P103: =ROUND(K103*'Irish Basis'!$C$8*'Irish Basis'!$C$5,2) | Q103: =ROUND(L103*'Irish Basis'!$C$12*'Irish Basis'!$C$5,2) | R103: =ROUND(SUM(N103:Q103),2) | S103: All-in specialist rate | T103: All-in (not split) | U103: 51.61 | V103: =IF(U103="","",ROUND(M103-U103,2)) | X103: Source publishes a specialist/sub-contract all-in rate; no labour/plant/material build-up exists to derive from.
A104: 260 | B104: IMG_0068 | C104: CLASS C: GEOTECHNICAL AND OTHER SPECIALIST PROCESSES | D104: 01 DRILLING FOR GROUT HOLES | E104: Horizontally or downwards at an angle less than 45 deg to the horizontal | F104: depth ne 5 m | G104: m | I104: 0 | J104: 0 | K104: 0 | L104: 30.76 | M104: =ROUND(SUM(I104:L104),2) | N104: =ROUND(I104*'Irish Basis'!$C$6*'Irish Basis'!$C$5,2) | O104: =ROUND(J104*'Irish Basis'!$C$7*'Irish Basis'!$C$5,2) | P104: =ROUND(K104*'Irish Basis'!$C$8*'Irish Basis'!$C$5,2) | Q104: =ROUND(L104*'Irish Basis'!$C$12*'Irish Basis'!$C$5,2) | R104: =ROUND(SUM(N104:Q104),2) | S104: All-in specialist rate | T104: All-in (not split) | U104: 30.76 | V104: =IF(U104="","",ROUND(M104-U104,2)) | X104: Source publishes a specialist/sub-contract all-in rate; no labour/plant/material build-up exists to derive from.
A105: 261 | B105: IMG_0068 | C105: CLASS C: GEOTECHNICAL AND OTHER SPECIALIST PROCESSES | D105: 01 DRILLING FOR GROUT HOLES | E105: Horizontally or downwards at an angle less than 45 deg to the horizontal | F105: depth 5-10 m | G105: m | I105: 0 | J105: 0 | K105: 0 | L105: 35.61 | M105: =ROUND(SUM(I105:L105),2) | N105: =ROUND(I105*'Irish Basis'!$C$6*'Irish Basis'!$C$5,2) | O105: =ROUND(J105*'Irish Basis'!$C$7*'Irish Basis'!$C$5,2) | P105: =ROUND(K105*'Irish Basis'!$C$8*'Irish Basis'!$C$5,2) | Q105: =ROUND(L105*'Irish Basis'!$C$12*'Irish Basis'!$C$5,2) | R105: =ROUND(SUM(N105:Q105),2) | S105: All-in specialist rate | T105: All-in (not split) | U105: 35.61 | V105: =IF(U105="","",ROUND(M105-U105,2)) | X105: Source publishes a specialist/sub-contract all-in rate; no labour/plant/material build-up exists to derive from.
A106: 262 | B106: IMG_0068 | C106: CLASS C: GEOTECHNICAL AND OTHER SPECIALIST PROCESSES | D106: 01 DRILLING FOR GROUT HOLES | E106: Horizontally or downwards at an angle less than 45 deg to the horizontal | F106: depth 10-20 m | G106: m | I106: 0 | J106: 0 | K106: 0 | L106: 42.19 | M106: =ROUND(SUM(I106:L106),2) | N106: =ROUND(I106*'Irish Basis'!$C$6*'Irish Basis'!$C$5,2) | O106: =ROUND(J106*'Irish Basis'!$C$7*'Irish Basis'!$C$5,2) | P106: =ROUND(K106*'Irish Basis'!$C$8*'Irish Basis'!$C$5,2) | Q106: =ROUND(L106*'Irish Basis'!$C$12*'Irish Basis'!$C$5,2) | R106: =ROUND(SUM(N106:Q106),2) | S106: All-in specialist rate | T106: All-in (not split) | U106: 42.19 | V106: =IF(U106="","",ROUND(M106-U106,2)) | X106: Source publishes a specialist/sub-contract all-in rate; no labour/plant/material build-up exists to derive from.
A107: 263 | B107: IMG_0068 | C107: CLASS C: GEOTECHNICAL AND OTHER SPECIALIST PROCESSES | D107: 01 DRILLING FOR GROUT HOLES | E107: Horizontally or downwards at an angle less than 45 deg to the horizontal | F107: depth 20-30 m | G107: m | I107: 0 | J107: 0 | K107: 0 | L107: 51.61 | M107: =ROUND(SUM(I107:L107),2) | N107: =ROUND(I107*'Irish Basis'!$C$6*'Irish Basis'!$C$5,2) | O107: =ROUND(J107*'Irish Basis'!$C$7*'Irish Basis'!$C$5,2) | P107: =ROUND(K107*'Irish Basis'!$C$8*'Irish Basis'!$C$5,2) | Q107: =ROUND(L107*'Irish Basis'!$C$12*'Irish Basis'!$C$5,2) | R107: =ROUND(SUM(N107:Q107),2) | S107: All-in specialist rate | T107: All-in (not split) | U107: 51.61 | V107: =IF(U107="","",ROUND(M107-U107,2)) | X107: Source publishes a specialist/sub-contract all-in rate; no labour/plant/material build-up exists to derive from.
... A147: 315 | B147: IMG_0069 | C147: CLASS C: GEOTECHNICAL AND OTHER SPECIALIST PROCESSES | D147: 04 GROUT MATERIALS AND INJECTION | E147: Injection | F147: cement/PFA grout | G147: t | I147: 0 | J147: 0 | K147: 0 | L147: 114.33 | M147: =ROUND(SUM(I147:L147),2) | N147: =ROUND(I147*'Irish Basis'!$C$6*'Irish Basis'!$C$5,2) | O147: =ROUND(J147*'Irish Basis'!$C$7*'Irish Basis'!$C$5,2) | P147: =ROUND(K147*'Irish Basis'!$C$8*'Irish Basis'!$C$5,2) | Q147: =ROUND(L147*'Irish Basis'!$C$12*'Irish Basis'!$C$5,2) | R147: =ROUND(SUM(N147:Q147),2) | S147: All-in specialist rate | T147: All-in (not split) | U147: 114.33 | V147: =IF(U147="","",ROUND(M147-U147,2)) | X147: Source publishes a specialist/sub-contract all-in rate; no labour/plant/material build-up exists to derive from.
A148: 319 | B148: IMG_0069 | C148: CLASS C: GEOTECHNICAL AND OTHER SPECIALIST PROCESSES | D148: 05 DIAPHRAGM WALLS | F148: Establishment of standard plant and equipment including bentonite storage tanks and removal on completion | G148: item | I148: 0 | J148: 0 | K148: 0 | L148: 549099.11 | M148: =ROUND(SUM(I148:L148),2) | N148: =ROUND(I148*'Irish Basis'!$C$6*'Irish Basis'!$C$5,2) | O148: =ROUND(J148*'Irish Basis'!$C$7*'Irish Basis'!$C$5,2) | P148: =ROUND(K148*'Irish Basis'!$C$8*'Irish Basis'!$C$5,2) | Q148: =ROUND(L148*'Irish Basis'!$C$12*'Irish Basis'!$C$5,2) | R148: =ROUND(SUM(N148:Q148),2) | S148: All-in specialist rate | T148: All-in (not split) | U148: 549099.11 | V148: =IF(U148="","",ROUND(M148-U148,2)) | W148: Probable source error — verify | X148: Source publishes a specialist/sub-contract all-in rate; no labour/plant/material build-up exists to derive from. This is 28x the next highest item in the class (£19,700.58) and out of line with comparable rates in the same section — likely a mis-read digit in the source scan. Verify before use.
A149: 320 | B149: IMG_0069 | C149: CLASS C: GEOTECHNICAL AND OTHER SPECIALIST PROCESSES | D149: 05 DIAPHRAGM WALLS | F149: Standing time | G149: hour | I149: 0 | J149: 0 | K149: 0 | L149: 1406.91 | M149: =ROUND(SUM(I149:L149),2) | N149: =ROUND(I149*'Irish Basis'!$C$6*'Irish Basis'!$C$5,2) | O149: =ROUND(J149*'Irish Basis'!$C$7*'Irish Basis'!$C$5,2) | P149: =ROUND(K149*'Irish Basis'!$C$8*'Irish Basis'!$C$5,2) | Q149: =ROUND(L149*'Irish Basis'!$C$12*'Irish Basis'!$C$5,2) | R149: =ROUND(SUM(N149:Q149),2) | S149: All-in specialist rate | T149: All-in (not split) | U149: 1406.91 | V149: =IF(U149="","",ROUND(M149-U149,2)) | X149: Source publishes a specialist/sub-contract all-in rate; no labour/plant/material build-up exists to derive from.
A150: 321 | B150: IMG_0069 | C150: CLASS C: GEOTECHNICAL AND OTHER SPECIALIST PROCESSES | D150: 05 DIAPHRAGM WALLS | F150: Excavation, disposal of soil and placing of concrete | G150: m3 | I150: 0 | J150: 0 | K150: 0 | L150: 713.14 | M150: =ROUND(SUM(I150:L150),2) | N150: =ROUND(I150*'Irish Basis'!$C$6*'Irish Basis'!$C$5,2) | O150: =ROUND(J150*'Irish Basis'!$C$7*'Irish Basis'!$C$5,2) | P150: =ROUND(K150*'Irish Basis'!$C$8*'Irish Basis'!$C$5,2) | Q150: =ROUND(L150*'Irish Basis'!$C$12*'Irish Basis'!$C$5,2) | R150: =ROUND(SUM(N150:Q150),2) | S150: All-in specialist rate | T150: All-in (not split) | U150: 713.14 | V150: =IF(U150="","",ROUND(M150-U150,2)) | X150: Source publishes a specialist/sub-contract all-in rate; no labour/plant/material build-up exists to derive from.
A151: 322 | B151: IMG_0069 | C151: CLASS C: GEOTECHNICAL AND OTHER SPECIALIST PROCESSES | D151: 05 DIAPHRAGM WALLS | F151: Provide and place reinforcement cages | G151: tonne | I151: 0 | J151: 0 | K151: 0 | L151: 1215.52 | M151: =ROUND(SUM(I151:L151),2) | N151: =ROUND(I151*'Irish Basis'!$C$6*'Irish Basis'!$C$5,2) | O151: =ROUND(J151*'Irish Basis'!$C$7*'Irish Basis'!$C$5,2) | P151: =ROUND(K151*'Irish Basis'!$C$8*'Irish Basis'!$C$5,2) | Q151: =ROUND(L151*'Irish Basis'!$C$12*'Irish Basis'!$C$5,2) | R151: =ROUND(SUM(N151:Q151),2) | S151: All-in specialist rate | T151: All-in (not split) | U151: 1215.52 | V151: =IF(U151="","",ROUND(M151-U151,2)) | X151: Source publishes a specialist/sub-contract all-in rate; no labour/plant/material build-up exists to derive from.
A152: 323 | B152: IMG_0069 | C152: CLASS C: GEOTECHNICAL AND OTHER SPECIALIST PROCESSES | D152: 05 DIAPHRAGM WALLS | F152: Excavate/chisel in hard material/rock | G152: hour | I152: 0 | J152: 0 | K152: 0 | L152: 1579.31 | M152: =ROUND(SUM(I152:L152),2) | N152: =ROUND(I152*'Irish Basis'!$C$6*'Irish Basis'!$C$5,2) | O152: =ROUND(J152*'Irish Basis'!$C$7*'Irish Basis'!$C$5,2) | P152: =ROUND(K152*'Irish Basis'!$C$8*'Irish Basis'!$C$5,2) | Q152: =ROUND(L152*'Irish Basis'!$C$12*'Irish Basis'!$C$5,2) | R152: =ROUND(SUM(N152:Q152),2) | S152: All-in specialist rate | T152: All-in (not split) | U152: 1579.31 | V152: =IF(U152="","",ROUND(M152-U152,2)) | X152: Source publishes a specialist/sub-contract all-in rate; no labour/plant/material build-up exists to derive from.
A153: 324 | B153: IMG_0069 | C153: CLASS C: GEOTECHNICAL AND OTHER SPECIALIST PROCESSES | D153: 05 DIAPHRAGM WALLS | F153: Waterproofed joints | G153: m | I153: 0 | J153: 0 | K153: 0 | L153: 10.54 | M153: =ROUND(SUM(I153:L153),2) | N153: =ROUND(I153*'Irish Basis'!$C$6*'Irish Basis'!$C$5,2) | O153: =ROUND(J153*'Irish Basis'!$C$7*'Irish Basis'!$C$5,2) | P153: =ROUND(K153*'Irish Basis'!$C$8*'Irish Basis'!$C$5,2) | Q153: =ROUND(L153*'Irish Basis'!$C$12*'Irish Basis'!$C$5,2) | R153: =ROUND(SUM(N153:Q153),2) | S153: All-in specialist rate | T153: All-in (not split) | U153: 10.54 | V153: =IF(U153="","",ROUND(M153-U153,2)) | X153: Source publishes a specialist/sub-contract all-in rate; no labour/plant/material build-up exists to derive from.
A154: 325 | B154: IMG_0069 | C154: CLASS C: GEOTECHNICAL AND OTHER SPECIALIST PROCESSES | D154: 05 DIAPHRAGM WALLS | F154: Guide walls (twin) | G154: m | I154: 0 | J154: 0 | K154: 0 | L154: 861.57 | M154: =ROUND(SUM(I154:L154),2) | N154: =ROUND(I154*'Irish Basis'!$C$6*'Irish Basis'!$C$5,2) | O154: =ROUND(J154*'Irish Basis'!$C$7*'Irish Basis'!$C$5,2) | P154: =ROUND(K154*'Irish Basis'!$C$8*'Irish Basis'!$C$5,2) | Q154: =ROUND(L154*'Irish Basis'!$C$12*'Irish Basis'!$C$5,2) | R154: =ROUND(SUM(N154:Q154),2) | S154: All-in specialist rate | T154: All-in (not split) | U154: 861.57 | V154: =IF(U154="","",ROUND(M154-U154,2)) | X154: Source publishes a specialist/sub-contract all-in rate; no labour/plant/material build-up exists to derive from.
A155: 329 | B155: IMG_0069 | C155: CLASS C: GEOTECHNICAL AND OTHER SPECIALIST PROCESSES | D155: 06 GROUND REINFORCEMENT | F155: Establishment of standard plant and equipment and removal on completion | G155: item | I155: 0 | J155: 0 | K155: 0 | L155: 18125.94 | M155: =ROUND(SUM(I155:L155),2) | N155: =ROUND(I155*'Irish Basis'!$C$6*'Irish Basis'!$C$5,2) | O155: =ROUND(J155*'Irish Basis'!$C$7*'Irish Basis'!$C$5,2) | P155: =ROUND(K155*'Irish Basis'!$C$8*'Irish Basis'!$C$5,2) | Q155: =ROUND(L155*'Irish Basis'!$C$12*'Irish Basis'!$C$5,2) | R155: =ROUND(SUM(N155:Q155),2) | S155: All-in specialist rate | T155: All-in (not split) | U155: 18125.94 | V155: =IF(U155="","",ROUND(M155-U155,2)) | X155: Source publishes a specialist/sub-contract all-in rate; no labour/plant/material build-up exists to derive from.
A156: 330 | B156: IMG_0069 | C156: CLASS C: GEOTECHNICAL AND OTHER SPECIALIST PROCESSES | D156: 06 GROUND REINFORCEMENT | F156: Standing time | G156: hour | I156: 0 | J156: 0 | K156: 0 | L156: 351.73 | M156: =ROUND(SUM(I156:L156),2) | N156: =ROUND(I156*'Irish Basis'!$C$6*'Irish Basis'!$C$5,2) | O156: =ROUND(J156*'Irish Basis'!$C$7*'Irish Basis'!$C$5,2) | P156: =ROUND(K156*'Irish Basis'!$C$8*'Irish Basis'!$C$5,2) | Q156: =ROUND(L156*'Irish Basis'!$C$12*'Irish Basis'!$C$5,2) | R156: =ROUND(SUM(N156:Q156),2) | S156: All-in specialist rate | T156: All-in (not split) | U156: 351.73 | V156: =IF(U156="","",ROUND(M156-U156,2)) | X156: Source publishes a specialist/sub-contract all-in rate; no labour/plant/material build-up exists to derive from.
A157: 332 | B157: IMG_0069 | C157: CLASS C: GEOTECHNICAL AND OTHER SPECIALIST PROCESSES | D157: 06 GROUND REINFORCEMENT | E157: Ground anchorages; temporary or permanent | F157: 15.0 m maximum depth; in rock, alluvial or clay; 0-50 t load | G157: m | I157: 0 | J157: 0 | K157: 0 | L157: 62.32 | M157: =ROUND(SUM(I157:L157),2) | N157: =ROUND(I157*'Irish Basis'!$C$6*'Irish Basis'!$C$5,2) | O157: =ROUND(J157*'Irish Basis'!$C$7*'Irish Basis'!$C$5,2) | P157: =ROUND(K157*'Irish Basis'!$C$8*'Irish Basis'!$C$5,2) | Q157: =ROUND(L157*'Irish Basis'!$C$12*'Irish Basis'!$C$5,2) | R157: =ROUND(SUM(N157:Q157),2) | S157: All-in specialist rate | T157: All-in (not split) | U157: 62.32 | V157: =IF(U157="","",ROUND(M157-U157,2)) | X157: Source publishes a specialist/sub-contract all-in rate; no labour/plant/material build-up exists to derive from.
A158: 333 | B158: IMG_0069 | C158: CLASS C: GEOTECHNICAL AND OTHER SPECIALIST PROCESSES | D158: 06 GROUND REINFORCEMENT | E158: Ground anchorages; temporary or permanent | F158: 15.0 m maximum depth; in rock or alluvial; 50-90 t load | G158: m | I158: 0 | J158: 0 | K158: 0 | L158: 88.02 | M158: =ROUND(SUM(I158:L158),2) | N158: =ROUND(I158*'Irish Basis'!$C$6*'Irish Basis'!$C$5,2) | O158: =ROUND(J158*'Irish Basis'!$C$7*'Irish Basis'!$C$5,2) | P158: =ROUND(K158*'Irish Basis'!$C$8*'Irish Basis'!$C$5,2) | Q158: =ROUND(L158*'Irish Basis'!$C$12*'Irish Basis'!$C$5,2) | R158: =ROUND(SUM(N158:Q158),2) | S158: All-in specialist rate | T158: All-in (not split) | U158: 88.02 | V158: =IF(U158="","",ROUND(M158-U158,2)) | X158: Source publishes a specialist/sub-contract all-in rate; no labour/plant/material build-up exists to derive from.
A159: 334 | B159: IMG_0069 | C159: CLASS C: GEOTECHNICAL AND OTHER SPECIALIST PROCESSES | D159: 06 GROUND REINFORCEMENT | E159: Ground anchorages; temporary or permanent | F159: 15.0 m maximum depth; in rock only; 90-150 t load | G159: m | I159: 0 | J159: 0 | K159: 0 | L159: 181.09 | M159: =ROUND(SUM(I159:L159),2) | N159: =ROUND(I159*'Irish Basis'!$C$6*'Irish Basis'!$C$5,2) | O159: =ROUND(J159*'Irish Basis'!$C$7*'Irish Basis'!$C$5,2) | P159: =ROUND(K159*'Irish Basis'!$C$8*'Irish Basis'!$C$5,2) | Q159: =ROUND(L159*'Irish Basis'!$C$12*'Irish Basis'!$C$5,2) | R159: =ROUND(SUM(N159:Q159),2) | S159: All-in specialist rate | T159: All-in (not split) | U159: 181.09 | V159: =IF(U159="","",ROUND(M159-U159,2)) | X159: Source publishes a specialist/sub-contract all-in rate; no labour/plant/material build-up exists to derive from.
A160: 336 | B160: IMG_0069 | C160: CLASS C: GEOTECHNICAL AND OTHER SPECIALIST PROCESSES | D160: 06 GROUND REINFORCEMENT | E160: Temporary tendons | F160: in rock, alluvial or clay; 0-50 t load | G160: m | I160: 0 | J160: 0 | K160: 0 | L160: 47.76 | M160: =ROUND(SUM(I160:L160),2) | N160: =ROUND(I160*'Irish Basis'!$C$6*'Irish Basis'!$C$5,2) | O160: =ROUND(J160*'Irish Basis'!$C$7*'Irish Basis'!$C$5,2) | P160: =ROUND(K160*'Irish Basis'!$C$8*'Irish Basis'!$C$5,2) | Q160: =ROUND(L160*'Irish Basis'!$C$12*'Irish Basis'!$C$5,2) | R160: =ROUND(SUM(N160:Q160),2) | S160: All-in specialist rate | T160: All-in (not split) | U160: 47.76 | V160: =IF(U160="","",ROUND(M160-U160,2)) | X160: Source publishes a specialist/sub-contract all-in rate; no labour/plant/material build-up exists to derive from.
A161: 337 | B161: IMG_0069 | C161: CLASS C: GEOTECHNICAL AND OTHER SPECIALIST PROCESSES | D161: 06 GROUND REINFORCEMENT | E161: Temporary tendons | F161: in rock or alluvial; 50-90 t load | G161: m | I161: 0 | J161: 0 | K161: 0 | L161: 69.12 | M161: =ROUND(SUM(I161:L161),2) | N161: =ROUND(I161*'Irish Basis'!$C$6*'Irish Basis'!$C$5,2) | O161: =ROUND(J161*'Irish Basis'!$C$7*'Irish Basis'!$C$5,2) | P161: =ROUND(K161*'Irish Basis'!$C$8*'Irish Basis'!$C$5,2) | Q161: =ROUND(L161*'Irish Basis'!$C$12*'Irish Basis'!$C$5,2) | R161: =ROUND(SUM(N161:Q161),2) | S161: All-in specialist rate | T161: All-in (not split) | U161: 69.12 | V161: =IF(U161="","",ROUND(M161-U161,2)) | X161: Source publishes a specialist/sub-contract all-in rate; no labour/plant/material build-up exists to derive from.
A162: 338 | B162: IMG_0069 | C162: CLASS C: GEOTECHNICAL AND OTHER SPECIALIST PROCESSES | D162: 06 GROUND REINFORCEMENT | E162: Temporary tendons | F162: in rock only; 90-150 t load | G162: m | I162: 0 | J162: 0 | K162: 0 | L162: 91.75 | M162: =ROUND(SUM(I162:L162),2) | N162: =ROUND(I162*'Irish Basis'!$C$6*'Irish Basis'!$C$5,2) | O162: =ROUND(J162*'Irish Basis'!$C$7*'Irish Basis'!$C$5,2) | P162: =ROUND(K162*'Irish Basis'!$C$8*'Irish Basis'!$C$5,2) | Q162: =ROUND(L162*'Irish Basis'!$C$12*'Irish Basis'!$C$5,2) | R162: =ROUND(SUM(N162:Q162),2) | S162: All-in specialist rate | T162: All-in (not split) | U162: 91.75 | V162: =IF(U162="","",ROUND(M162-U162,2)) | X162: Source publishes a specialist/sub-contract all-in rate; no labour/plant/material build-up exists to derive from.
A163: 340 | B163: IMG_0069 | C163: CLASS C: GEOTECHNICAL AND OTHER SPECIALIST PROCESSES | D163: 06 GROUND REINFORCEMENT | E163: Permanent tendons | F163: in rock, alluvial or clay; 0-50 t load | G163: m | I163: 0 | J163: 0 | K163: 0 | L163: 47.76 | M163: =ROUND(SUM(I163:L163),2) | N163: =ROUND(I163*'Irish Basis'!$C$6*'Irish Basis'!$C$5,2) | O163: =ROUND(J163*'Irish Basis'!$C$7*'Irish Basis'!$C$5,2) | P163: =ROUND(K163*'Irish Basis'!$C$8*'Irish Basis'!$C$5,2) | Q163: =ROUND(L163*'Irish Basis'!$C$12*'Irish Basis'!$C$5,2) | R163: =ROUND(SUM(N163:Q163),2) | S163: All-in specialist rate | T163: All-in (not split) | U163: 47.76 | V163: =IF(U163="","",ROUND(M163-U163,2)) | X163: Source publishes a specialist/sub-contract all-in rate; no labour/plant/material build-up exists to derive from.
A164: 341 | B164: IMG_0069 | C164: CLASS C: GEOTECHNICAL AND OTHER SPECIALIST PROCESSES | D164: 06 GROUND REINFORCEMENT | E164: Permanent tendons | F164: in rock or alluvial; 50-90 t load | G164: m | I164: 0 | J164: 0 | K164: 0 | L164: 69.12 | M164: =ROUND(SUM(I164:L164),2) | N164: =ROUND(I164*'Irish Basis'!$C$6*'Irish Basis'!$C$5,2) | O164: =ROUND(J164*'Irish Basis'!$C$7*'Irish Basis'!$C$5,2) | P164: =ROUND(K164*'Irish Basis'!$C$8*'Irish Basis'!$C$5,2) | Q164: =ROUND(L164*'Irish Basis'!$C$12*'Irish Basis'!$C$5,2) | R164: =ROUND(SUM(N164:Q164),2) | S164: All-in specialist rate | T164: All-in (not split) | U164: 69.12 | V164: =IF(U164="","",ROUND(M164-U164,2)) | X164: Source publishes a specialist/sub-contract all-in rate; no labour/plant/material build-up exists to derive from.
A165: 342 | B165: IMG_0069 | C165: CLASS C: GEOTECHNICAL AND OTHER SPECIALIST PROCESSES | D165: 06 GROUND REINFORCEMENT | E165: Permanent tendons | F165: in rock only; 90-150 t load | G165: m | I165: 0 | J165: 0 | K165: 0 | L165: 146.79 | M165: =ROUND(SUM(I165:L165),2) | N165: =ROUND(I165*'Irish Basis'!$C$6*'Irish Basis'!$C$5,2) | O165: =ROUND(J165*'Irish Basis'!$C$7*'Irish Basis'!$C$5,2) | P165: =ROUND(K165*'Irish Basis'!$C$8*'Irish Basis'!$C$5,2) | Q165: =ROUND(L165*'Irish Basis'!$C$12*'Irish Basis'!$C$5,2) | R165: =ROUND(SUM(N165:Q165),2) | S165: All-in specialist rate | T165: All-in (not split) | U165: 146.79 | V165: =IF(U165="","",ROUND(M165-U165,2)) | X165: Source publishes a specialist/sub-contract all-in rate; no labour/plant/material build-up exists to derive from.
A166: 346 | B166: IMG_0069 | C166: CLASS C: GEOTECHNICAL AND OTHER SPECIALIST PROCESSES | D166: 07 SAND, BAND AND WICK DRAINS | F166: Establishment of standard plant and equipment and removal on completion | G166: item | I166: 0 | J166: 0 | K166: 0 | L166: 10875.57 | M166: =ROUND(SUM(I166:L166),2) | N166: =ROUND(I166*'Irish Basis'!$C$6*'Irish Basis'!$C$5,2) | O166: =ROUND(J166*'Irish Basis'!$C$7*'Irish Basis'!$C$5,2) | P166: =ROUND(K166*'Irish Basis'!$C$8*'Irish Basis'!$C$5,2) | Q166: =ROUND(L166*'Irish Basis'!$C$12*'Irish Basis'!$C$5,2) | R166: =ROUND(SUM(N166:Q166),2) | S166: All-in specialist rate | T166: All-in (not split) | U166: 10875.57 | V166: =IF(U166="","",ROUND(M166-U166,2)) | X166: Source publishes a specialist/sub-contract all-in rate; no labour/plant/material build-up exists to derive from.
A167: 347 | B167: IMG_0069 | C167: CLASS C: GEOTECHNICAL AND OTHER SPECIALIST PROCESSES | D167: 07 SAND, BAND AND WICK DRAINS | F167: Standing time | G167: hour | I167: 0 | J167: 0 | K167: 0 | L167: 351.73 | M167: =ROUND(SUM(I167:L167),2) | N167: =ROUND(I167*'Irish Basis'!$C$6*'Irish Basis'!$C$5,2) | O167: =ROUND(J167*'Irish Basis'!$C$7*'Irish Basis'!$C$5,2) | P167: =ROUND(K167*'Irish Basis'!$C$8*'Irish Basis'!$C$5,2) | Q167: =ROUND(L167*'Irish Basis'!$C$12*'Irish Basis'!$C$5,2) | R167: =ROUND(SUM(N167:Q167),2) | S167: All-in specialist rate | T167: All-in (not split) | U167: 351.73 | V167: =IF(U167="","",ROUND(M167-U167,2)) | X167: Source publishes a specialist/sub-contract all-in rate; no labour/plant/material build-up exists to derive from.
A168: 348 | B168: IMG_0069 | C168: CLASS C: GEOTECHNICAL AND OTHER SPECIALIST PROCESSES | D168: 07 SAND, BAND AND WICK DRAINS | F168: Set up installation equipment at each drain position Install drains maximum depth 10-15 m | G168: nr | I168: 0 | J168: 0 | K168: 0 | L168: 2.76 | M168: =ROUND(SUM(I168:L168),2) | N168: =ROUND(I168*'Irish Basis'!$C$6*'Irish Basis'!$C$5,2) | O168: =ROUND(J168*'Irish Basis'!$C$7*'Irish Basis'!$C$5,2) | P168: =ROUND(K168*'Irish Basis'!$C$8*'Irish Basis'!$C$5,2) | Q168: =ROUND(L168*'Irish Basis'!$C$12*'Irish Basis'!$C$5,2) | R168: =ROUND(SUM(N168:Q168),2) | S168: All-in specialist rate | T168: All-in (not split) | U168: 2.76 | V168: =IF(U168="","",ROUND(M168-U168,2)) | X168: Source publishes a specialist/sub-contract all-in rate; no labour/plant/material build-up exists to derive from.
A169: 349 | B169: IMG_0069 | C169: CLASS C: GEOTECHNICAL AND OTHER SPECIALIST PROCESSES | D169: 07 SAND, BAND AND WICK DRAINS | F169: Install drains maximum depth over 15 m | G169: m | I169: 0 | J169: 0 | K169: 0 | L169: 2.57 | M169: =ROUND(SUM(I169:L169),2) | N169: =ROUND(I169*'Irish Basis'!$C$6*'Irish Basis'!$C$5,2) | O169: =ROUND(J169*'Irish Basis'!$C$7*'Irish Basis'!$C$5,2) | P169: =ROUND(K169*'Irish Basis'!$C$8*'Irish Basis'!$C$5,2) | Q169: =ROUND(L169*'Irish Basis'!$C$12*'Irish Basis'!$C$5,2) | R169: =ROUND(SUM(N169:Q169),2) | S169: All-in specialist rate | T169: All-in (not split) | U169: 2.57 | V169: =IF(U169="","",ROUND(M169-U169,2)) | X169: Source publishes a specialist/sub-contract all-in rate; no labour/plant/material build-up exists to derive from.
A170: 351 | B170: IMG_0069 | C170: CLASS C: GEOTECHNICAL AND OTHER SPECIALIST PROCESSES | D170: 07 SAND, BAND AND WICK DRAINS | F170: establishment of standard drilling plant and equipment and removal on completion | G170: item | I170: 0 | J170: 0 | K170: 0 | L170: 3688.02 | M170: =ROUND(SUM(I170:L170),2) | N170: =ROUND(I170*'Irish Basis'!$C$6*'Irish Basis'!$C$5,2) | O170: =ROUND(J170*'Irish Basis'!$C$7*'Irish Basis'!$C$5,2) | P170: =ROUND(K170*'Irish Basis'!$C$8*'Irish Basis'!$C$5,2) | Q170: =ROUND(L170*'Irish Basis'!$C$12*'Irish Basis'!$C$5,2) | R170: =ROUND(SUM(N170:Q170),2) | S170: All-in specialist rate | T170: All-in (not split) | U170: 3688.02 | V170: =IF(U170="","",ROUND(M170-U170,2)) | X170: Source publishes a specialist/sub-contract all-in rate; no labour/plant/material build-up exists to derive from.
A171: 352 | B171: IMG_0069 | C171: CLASS C: GEOTECHNICAL AND OTHER SPECIALIST PROCESSES | D171: 07 SAND, BAND AND WICK DRAINS | F171: set up at each drain position | G171: nr | I171: 0 | J171: 0 | K171: 0 | L171: 8.94 | M171: =ROUND(SUM(I171:L171),2) | N171: =ROUND(I171*'Irish Basis'!$C$6*'Irish Basis'!$C$5,2) | O171: =ROUND(J171*'Irish Basis'!$C$7*'Irish Basis'!$C$5,2) | P171: =ROUND(K171*'Irish Basis'!$C$8*'Irish Basis'!$C$5,2) | Q171: =ROUND(L171*'Irish Basis'!$C$12*'Irish Basis'!$C$5,2) | R171: =ROUND(SUM(N171:Q171),2) | S171: All-in specialist rate | T171: All-in (not split) | U171: 8.94 | V171: =IF(U171="","",ROUND(M171-U171,2)) | X171: Source publishes a specialist/sub-contract all-in rate; no labour/plant/material build-up exists to derive from.
A172: 353 | B172: IMG_0069 | C172: CLASS C: GEOTECHNICAL AND OTHER SPECIALIST PROCESSES | D172: 07 SAND, BAND AND WICK DRAINS | F172: drilling for vertical band drains up to a maximum depth of 3 m | G172: m | I172: 0 | J172: 0 | K172: 0 | L172: 19.4 | M172: =ROUND(SUM(I172:L172),2) | N172: =ROUND(I172*'Irish Basis'!$C$6*'Irish Basis'!$C$5,2) | O172: =ROUND(J172*'Irish Basis'!$C$7*'Irish Basis'!$C$5,2) | P172: =ROUND(K172*'Irish Basis'!$C$8*'Irish Basis'!$C$5,2) | Q172: =ROUND(L172*'Irish Basis'!$C$12*'Irish Basis'!$C$5,2) | R172: =ROUND(SUM(N172:Q172),2) | S172: All-in specialist rate | T172: All-in (not split) | U172: 19.4 | V172: =IF(U172="","",ROUND(M172-U172,2)) | X172: Source publishes a specialist/sub-contract all-in rate; no labour/plant/material build-up exists to derive from.
A173: 361 | B173: IMG_0070 | C173: CLASS C: GEOTECHNICAL AND OTHER SPECIALIST PROCESSES | D173: 08 VIBRO-FLOTATION AND DYNAMIC COMPACTION | E173: Plant mobilization | F173: establishment of standard plant and equipment and removal on completion | G173: m | I173: 0 | J173: 0 | K173: 0 | L173: 7249.14 | M173: =ROUND(SUM(I173:L173),2) | N173: =ROUND(I173*'Irish Basis'!$C$6*'Irish Basis'!$C$5,2) | O173: =ROUND(J173*'Irish Basis'!$C$7*'Irish Basis'!$C$5,2) | P173: =ROUND(K173*'Irish Basis'!$C$8*'Irish Basis'!$C$5,2) | Q173: =ROUND(L173*'Irish Basis'!$C$12*'Irish Basis'!$C$5,2) | R173: =ROUND(SUM(N173:Q173),2) | S173: All-in specialist rate | T173: All-in (not split) | U173: 7249.14 | V173: =IF(U173="","",ROUND(M173-U173,2)) | X173: Source publishes a specialist/sub-contract all-in rate; no labour/plant/material build-up exists to derive from.
A174: 362 | B174: IMG_0070 | C174: CLASS C: GEOTECHNICAL AND OTHER SPECIALIST PROCESSES | D174: 08 VIBRO-FLOTATION AND DYNAMIC COMPACTION | E174: Plant mobilization | F174: standing time | G174: m | I174: 0 | J174: 317.24 | K174: 0 | L174: 0 | M174: =ROUND(SUM(I174:L174),2) | N174: =ROUND(I174*'Irish Basis'!$C$6*'Irish Basis'!$C$5,2) | O174: =ROUND(J174*'Irish Basis'!$C$7*'Irish Basis'!$C$5,2) | P174: =ROUND(K174*'Irish Basis'!$C$8*'Irish Basis'!$C$5,2) | Q174: =ROUND(L174*'Irish Basis'!$C$12*'Irish Basis'!$C$5,2) | R174: =ROUND(SUM(N174:Q174),2) | S174: Stated build-up | T174: High | U174: 317.24 | V174: =IF(U174="","",ROUND(M174-U174,2)) | X174: Labour + plant + material as published; reconciles to the published rate.
A175: 364 | B175: IMG_0070 | C175: CLASS C: GEOTECHNICAL AND OTHER SPECIALIST PROCESSES | D175: 08 VIBRO-FLOTATION AND DYNAMIC COMPACTION | E175: Construct stone columns to a depth ne 4 m | F175: dry formed | G175: m | H175: 1 | I175: 73.82 | J175: 0 | K175: 0 | L175: 0 | M175: =ROUND(SUM(I175:L175),2) | N175: =ROUND(I175*'Irish Basis'!$C$6*'Irish Basis'!$C$5,2) | O175: =ROUND(J175*'Irish Basis'!$C$7*'Irish Basis'!$C$5,2) | P175: =ROUND(K175*'Irish Basis'!$C$8*'Irish Basis'!$C$5,2) | Q175: =ROUND(L175*'Irish Basis'!$C$12*'Irish Basis'!$C$5,2) | R175: =ROUND(SUM(N175:Q175),2) | S175: Stated build-up | T175: High | U175: 73.82 | V175: =IF(U175="","",ROUND(M175-U175,2)) | X175: Labour + plant + material as published; reconciles to the published rate.
A176: 365 | B176: IMG_0070 | C176: CLASS C: GEOTECHNICAL AND OTHER SPECIALIST PROCESSES | D176: 08 VIBRO-FLOTATION AND DYNAMIC COMPACTION | E176: Construct stone columns to a depth ne 4 m | F176: water jet formed | G176: m | I176: 0 | J176: 0 | K176: 0 | L176: 489.89 | M176: =ROUND(SUM(I176:L176),2) | N176: =ROUND(I176*'Irish Basis'!$C$6*'Irish Basis'!$C$5,2) | O176: =ROUND(J176*'Irish Basis'!$C$7*'Irish Basis'!$C$5,2) | P176: =ROUND(K176*'Irish Basis'!$C$8*'Irish Basis'!$C$5,2) | Q176: =ROUND(L176*'Irish Basis'!$C$12*'Irish Basis'!$C$5,2) | R176: =ROUND(SUM(N176:Q176),2) | S176: All-in specialist rate | T176: All-in (not split) | U176: 489.89 | V176: =IF(U176="","",ROUND(M176-U176,2)) | X176: Source publishes a specialist/sub-contract all-in rate; no labour/plant/material build-up exists to derive from.
A177: 367 | B177: IMG_0070 | C177: CLASS C: GEOTECHNICAL AND OTHER SPECIALIST PROCESSES | D177: 08 VIBRO-FLOTATION AND DYNAMIC COMPACTION | E177: Plate bearing test | F177: ne 11 t or 2 hour duration | G177: nr | I177: 0 | J177: 0 | K177: 0 | L177: 761.83 | M177: =ROUND(SUM(I177:L177),2) | N177: =ROUND(I177*'Irish Basis'!$C$6*'Irish Basis'!$C$5,2) | O177: =ROUND(J177*'Irish Basis'!$C$7*'Irish Basis'!$C$5,2) | P177: =ROUND(K177*'Irish Basis'!$C$8*'Irish Basis'!$C$5,2) | Q177: =ROUND(L177*'Irish Basis'!$C$12*'Irish Basis'!$C$5,2) | R177: =ROUND(SUM(N177:Q177),2) | S177: All-in specialist rate | T177: All-in (not split) | U177: 761.83 | V177: =IF(U177="","",ROUND(M177-U177,2)) | X177: Source publishes a specialist/sub-contract all-in rate; no labour/plant/material build-up exists to derive from.
A178: 368 | B178: IMG_0070 | C178: CLASS C: GEOTECHNICAL AND OTHER SPECIALIST PROCESSES | D178: 08 VIBRO-FLOTATION AND DYNAMIC COMPACTION | E178: Plate bearing test | F178: zone specification testing | G178: nr | I178: 0 | J178: 0 | K178: 0 | L178: 15236.55 | M178: =ROUND(SUM(I178:L178),2) | N178: =ROUND(I178*'Irish Basis'!$C$6*'Irish Basis'!$C$5,2) | O178: =ROUND(J178*'Irish Basis'!$C$7*'Irish Basis'!$C$5,2) | P178: =ROUND(K178*'Irish Basis'!$C$8*'Irish Basis'!$C$5,2) | Q178: =ROUND(L178*'Irish Basis'!$C$12*'Irish Basis'!$C$5,2) | R178: =ROUND(SUM(N178:Q178),2) | S178: All-in specialist rate | T178: All-in (not split) | U178: 15236.55 | V178: =IF(U178="","",ROUND(M178-U178,2)) | X178: Source publishes a specialist/sub-contract all-in rate; no labour/plant/material build-up exists to derive from.
A179: 370 | B179: IMG_0070 | C179: CLASS C: GEOTECHNICAL AND OTHER SPECIALIST PROCESSES | D179: 08 VIBRO-FLOTATION AND DYNAMIC COMPACTION | E179: Vibro flotation | F179: Depth not exceeding 5 m | G179: m | H179: 0.6 | I179: 19.07 | J179: 56.33 | K179: 0 | L179: 2436.35 | M179: =ROUND(SUM(I179:L179),2) | N179: =ROUND(I179*'Irish Basis'!$C$6*'Irish Basis'!$C$5,2) | O179: =ROUND(J179*'Irish Basis'!$C$7*'Irish Basis'!$C$5,2) | P179: =ROUND(K179*'Irish Basis'!$C$8*'Irish Basis'!$C$5,2) | Q179: =ROUND(L179*'Irish Basis'!$C$12*'Irish Basis'!$C$5,2) | R179: =ROUND(SUM(N179:Q179),2) | S179: Stated components + specialist balance | T179: Medium | U179: 2511.75 | V179: =IF(U179="","",ROUND(M179-U179,2)) | W179: Large unexplained balance | X179: Published plant/labour retained; the £2,436.35 balance of the specialist all-in rate is not broken down in the source.
A180: 371 | B180: IMG_0070 | C180: CLASS C: GEOTECHNICAL AND OTHER SPECIALIST PROCESSES | D180: 08 VIBRO-FLOTATION AND DYNAMIC COMPACTION | E180: Vibro flotation | F180: Depth: 5 m-10 m | G180: m | H180: 1.5 | I180: 47.69 | J180: 29.8 | K180: 0 | L180: 3070.38 | M180: =ROUND(SUM(I180:L180),2) | N180: =ROUND(I180*'Irish Basis'!$C$6*'Irish Basis'!$C$5,2) | O180: =ROUND(J180*'Irish Basis'!$C$7*'Irish Basis'!$C$5,2) | P180: =ROUND(K180*'Irish Basis'!$C$8*'Irish Basis'!$C$5,2) | Q180: =ROUND(L180*'Irish Basis'!$C$12*'Irish Basis'!$C$5,2) | R180: =ROUND(SUM(N180:Q180),2) | S180: Stated components + specialist balance | T180: Medium | U180: 3147.87 | V180: =IF(U180="","",ROUND(M180-U180,2)) | W180: Large unexplained balance | X180: Published plant/labour retained; the £3,070.38 balance of the specialist all-in rate is not broken down in the source.
A181: 372 | B181: IMG_0070 | C181: CLASS C: GEOTECHNICAL AND OTHER SPECIALIST PROCESSES | D181: 08 VIBRO-FLOTATION AND DYNAMIC COMPACTION | E181: Vibro flotation | F181: Depth: 10 m-20 m | G181: m | H181: 1.5 | I181: 47.69 | J181: 53.89 | K181: 0 | L181: 4283.89 | M181: =ROUND(SUM(I181:L181),2) | N181: =ROUND(I181*'Irish Basis'!$C$6*'Irish Basis'!$C$5,2) | O181: =ROUND(J181*'Irish Basis'!$C$7*'Irish Basis'!$C$5,2) | P181: =ROUND(K181*'Irish Basis'!$C$8*'Irish Basis'!$C$5,2) | Q181: =ROUND(L181*'Irish Basis'!$C$12*'Irish Basis'!$C$5,2) | R181: =ROUND(SUM(N181:Q181),2) | S181: Stated components + specialist balance | T181: Medium | U181: 4385.47 | V181: =IF(U181="","",ROUND(M181-U181,2)) | W181: Large unexplained balance | X181: Published plant/labour retained; the £4,283.89 balance of the specialist all-in rate is not broken down in the source.
A182: 373 | B182: IMG_0070 | C182: CLASS C: GEOTECHNICAL AND OTHER SPECIALIST PROCESSES | D182: 08 VIBRO-FLOTATION AND DYNAMIC COMPACTION | E182: Vibro flotation | F182: Depth: 30 m-40 m | G182: m | H182: 3 | I182: 95.37 | J182: 59.59 | K182: 0 | L182: 6924.55 | M182: =ROUND(SUM(I182:L182),2) | N182: =ROUND(I182*'Irish Basis'!$C$6*'Irish Basis'!$C$5,2) | O182: =ROUND(J182*'Irish Basis'!$C$7*'Irish Basis'!$C$5,2) | P182: =ROUND(K182*'Irish Basis'!$C$8*'Irish Basis'!$C$5,2) | Q182: =ROUND(L182*'Irish Basis'!$C$12*'Irish Basis'!$C$5,2) | R182: =ROUND(SUM(N182:Q182),2) | S182: Stated components + specialist balance | T182: Medium | U182: 7079.51 | V182: =IF(U182="","",ROUND(M182-U182,2)) | W182: Large unexplained balance | X182: Published plant/labour retained; the £6,924.55 balance of the specialist all-in rate is not broken down in the source.
A183: 378 | B183: IMG_0070 | C183: CLASS C: GEOTECHNICAL AND OTHER SPECIALIST PROCESSES | D183: 08 VIBRO-FLOTATION AND DYNAMIC COMPACTION | E183: DYNAMIC COMPACTION | F183: Establishment of standard plant and equipment and removal on completion. | G183: item | I183: 0 | J183: 0 | K183: 0 | L183: 19700.58 | M183: =ROUND(SUM(I183:L183),2) | N183: =ROUND(I183*'Irish Basis'!$C$6*'Irish Basis'!$C$5,2) | O183: =ROUND(J183*'Irish Basis'!$C$7*'Irish Basis'!$C$5,2) | P183: =ROUND(K183*'Irish Basis'!$C$8*'Irish Basis'!$C$5,2) | Q183: =ROUND(L183*'Irish Basis'!$C$12*'Irish Basis'!$C$5,2) | R183: =ROUND(SUM(N183:Q183),2) | S183: All-in specialist rate | T183: All-in (not split) | U183: 19700.58 | V183: =IF(U183="","",ROUND(M183-U183,2)) | X183: Source publishes a specialist/sub-contract all-in rate; no labour/plant/material build-up exists to derive from.
A184: 379 | B184: IMG_0070 | C184: CLASS C: GEOTECHNICAL AND OTHER SPECIALIST PROCESSES | D184: 08 VIBRO-FLOTATION AND DYNAMIC COMPACTION | E184: DYNAMIC COMPACTION | F184: Ground treatment | G184: m2 | I184: 0 | J184: 0 | K184: 0 | L184: 3.09 | M184: =ROUND(SUM(I184:L184),2) | N184: =ROUND(I184*'Irish Basis'!$C$6*'Irish Basis'!$C$5,2) | O184: =ROUND(J184*'Irish Basis'!$C$7*'Irish Basis'!$C$5,2) | P184: =ROUND(K184*'Irish Basis'!$C$8*'Irish Basis'!$C$5,2) | Q184: =ROUND(L184*'Irish Basis'!$C$12*'Irish Basis'!$C$5,2) | R184: =ROUND(SUM(N184:Q184),2) | S184: All-in specialist rate | T184: All-in (not split) | U184: 3.09 | V184: =IF(U184="","",ROUND(M184-U184,2)) | X184: Source publishes a specialist/sub-contract all-in rate; no labour/plant/material build-up exists to derive from.
A185: 380 | B185: IMG_0070 | C185: CLASS C: GEOTECHNICAL AND OTHER SPECIALIST PROCESSES | D185: 08 VIBRO-FLOTATION AND DYNAMIC COMPACTION | E185: DYNAMIC COMPACTION | F185: Laying free-draining granular blanket layer as both working surface and backfill material (300 mm thickness required of filter material) | G185: m2 | I185: 0 | J185: 0 | K185: 0 | L185: 15.04 | M185: =ROUND(SUM(I185:L185),2) | N185: =ROUND(I185*'Irish Basis'!$C$6*'Irish Basis'!$C$5,2) | O185: =ROUND(J185*'Irish Basis'!$C$7*'Irish Basis'!$C$5,2) | P185: =ROUND(K185*'Irish Basis'!$C$8*'Irish Basis'!$C$5,2) | Q185: =ROUND(L185*'Irish Basis'!$C$12*'Irish Basis'!$C$5,2) | R185: =ROUND(SUM(N185:Q185),2) | S185: All-in specialist rate | T185: All-in (not split) | U185: 15.04 | V185: =IF(U185="","",ROUND(M185-U185,2)) | X185: Source publishes a specialist/sub-contract all-in rate; no labour/plant/material build-up exists to derive from.
A186: 381 | B186: IMG_0070 | C186: CLASS C: GEOTECHNICAL AND OTHER SPECIALIST PROCESSES | D186: 08 VIBRO-FLOTATION AND DYNAMIC COMPACTION | E186: DYNAMIC COMPACTION | F186: Control testing including levelling, piezometers and penetrameter testing | G186: m2 | I186: 0 | J186: 0 | K186: 0 | L186: 6.61 | M186: =ROUND(SUM(I186:L186),2) | N186: =ROUND(I186*'Irish Basis'!$C$6*'Irish Basis'!$C$5,2) | O186: =ROUND(J186*'Irish Basis'!$C$7*'Irish Basis'!$C$5,2) | P186: =ROUND(K186*'Irish Basis'!$C$8*'Irish Basis'!$C$5,2) | Q186: =ROUND(L186*'Irish Basis'!$C$12*'Irish Basis'!$C$5,2) | R186: =ROUND(SUM(N186:Q186),2) | S186: All-in specialist rate | T186: All-in (not split) | U186: 6.61 | V186: =IF(U186="","",ROUND(M186-U186,2)) | X186: Source publishes a specialist/sub-contract all-in rate; no labour/plant/material build-up exists to derive from.
A187: 382 | B187: IMG_0070 | C187: CLASS C: GEOTECHNICAL AND OTHER SPECIALIST PROCESSES | D187: 08 VIBRO-FLOTATION AND DYNAMIC COMPACTION | E187: DYNAMIC COMPACTION | F187: Kentledge load test | G187: nr | I187: 0 | J187: 0 | K187: 0 | L187: 14108.16 | M187: =ROUND(SUM(I187:L187),2) | N187: =ROUND(I187*'Irish Basis'!$C$6*'Irish Basis'!$C$5,2) | O187: =ROUND(J187*'Irish Basis'!$C$7*'Irish Basis'!$C$5,2) | P187: =ROUND(K187*'Irish Basis'!$C$8*'Irish Basis'!$C$5,2) | Q187: =ROUND(L187*'Irish Basis'!$C$12*'Irish Basis'!$C$5,2) | R187: =ROUND(SUM(N187:Q187),2) | S187: All-in specialist rate | T187: All-in (not split) | U187: 14108.16 | V187: =IF(U187="","",ROUND(M187-U187,2)) | X187: Source publishes a specialist/sub-contract all-in rate; no labour/plant/material build-up exists to derive from.
A188: 385 | B188: IMG_0070 | C188: CLASS C: GEOTECHNICAL AND OTHER SPECIALIST PROCESSES | D188: 08 VIBRO-FLOTATION AND DYNAMIC COMPACTION | E188: CONSOLIDATION OF ABANDONED MINE WORKINGS | F188: Transport plant, labour and all equipment to and from site (max. 50 miles) | G188: item | I188: 0 | J188: 0 | K188: 0 | L188: 665.39 | M188: =ROUND(SUM(I188:L188),2) | N188: =ROUND(I188*'Irish Basis'!$C$6*'Irish Basis'!$C$5,2) | O188: =ROUND(J188*'Irish Basis'!$C$7*'Irish Basis'!$C$5,2) | P188: =ROUND(K188*'Irish Basis'!$C$8*'Irish Basis'!$C$5,2) | Q188: =ROUND(L188*'Irish Basis'!$C$12*'Irish Basis'!$C$5,2) | R188: =ROUND(SUM(N188:Q188),2) | S188: All-in specialist rate | T188: All-in (not split) | U188: 665.39 | V188: =IF(U188="","",ROUND(M188-U188,2)) | X188: Source publishes a specialist/sub-contract all-in rate; no labour/plant/material build-up exists to derive from.
...

Sheet Irish Basis
B1: Irish Basis — conversion inputs
B2: Every rate on 'Derived Rates' is converted to euro from these cells. Change one and all 3,793 items re-cost.
B4: Conversion inputs — edit the yellow cells
B5: GBP → EUR exchange rate | C5: 1.1694 | H5: Spot rate, August 2026. The 2026 year-to-date average is 1.1562 — use that instead for a budget or a fixed-price tender.
B6: Labour factor (Ireland ÷ UK) | C6: =G19 | H6: Calculated from the grade comparison below, so it follows the exchange rate. Overwrite with your own number if you have better evidence.
B7: Plant factor (Ireland ÷ UK) | C7: 1 | H7: ASSUMPTION — set to parity. No published Ireland-vs-UK plant differential was found. Plant is internationally traded capital equipment and the two hire markets share the same major suppliers. This is the weakest input here; override it if you have hire-desk quotes.
B8: Material factor (Ireland ÷ UK) | C8: 1 | H8: ASSUMPTION — set to parity. No published Ireland-vs-UK price-LEVEL series exists (Eurostat's construction PLIs dropped the UK after Brexit). Irish material inflation is running below the UK (3.2% vs 6.0% y/y to June 2026), so the gap is narrowing, not widening. Override with your own supplier data.
B9: Sub-contract mix — labour share | C9: 0.35 | H9: The assumed make-up of a specialist sub-contract package. Specialist trades (piling, tunnelling, demolition) are more labour and plant intensive than the book average.
B10: Sub-contract mix — plant share | C10: 0.3
B11: Sub-contract mix — material share | C11: 0.35
B12: Sub-contract factor (calculated) | C12: =ROUND(C9*C6+C10*C7+C11*C8,4) | H12: Blended from the three factors above using that mix. Applies to the 653 items carried as all-in specialist rates.
B14: How the labour factor was derived
B15: Irish grade (SEO) | C15: Ireland €/hr | D15: UK equivalent (CIJC) | E15: UK £/hr | F15: UK €/hr | G15: Ratio
B16: Craftsperson | C16: 23.74 | D16: Craft rate | E16: 16.4 | F16: =ROUND(E16*$C$5,2) | G16: =ROUND(C16/F16,4)
B17: Category A (skilled operative) | C17: 23.03 | D17: Skill Rate 3 | E17: 14.07 | F17: =ROUND(E17*$C$5,2) | G17: =ROUND(C17/F17,4)
B18: Category B (general operative) | C18: 21.37 | D18: General operative | E18: 13.18 | F18: =ROUND(E18*$C$5,2) | G18: =ROUND(C18/F18,4)
B19: Blended (equal weight) | G19: =ROUND(AVERAGE(G16:G18),4) | H19: Irish statutory construction rates run about a third above the UK equivalents once converted to euro. These are BASIC rates: employer on-costs differ too (UK NI 15% vs Irish PRSI ~11.25%), which would trim the premium slightly. Refine with your own all-in rates if you have them.
B21: Evidence behind each factor
B22: Labour | C22: Strong — statutory rates both sides, current, like-for-like grades | H22: Ireland: Sectoral Employment Order (Construction), rates effective 1 August 2026. UK: CIJC Working Rule Agreement, rates effective 20 July 2026.
B23: Exchange rate | C23: Strong — observable market rate | H23: GBP/EUR spot, August 2026 (~1.1694); 2026 year-to-date average 1.1562.
B24: Plant | C24: Weak — assumption, no source found | H24: No published Ireland-vs-UK plant hire differential located. Consumer hire-price guides for the two markets are not like-for-like on machine size.
B25: Material | C25: Weak — assumption, no source found | H25: No Ireland-vs-UK price-LEVEL series exists post-Brexit. Inflation RATES are available and diverging (CSO Ireland 3.2%, UK 6.0% y/y to June 2026) but rates of change cannot establish a level difference.
B26: Cross-check | C26: Top-down sanity check | H26: Arcadis International Construction Costs 2025 ranks Dublin 9th globally and Bristol 8th, with London 2nd — so overall Irish construction cost sits close to a major UK regional city, below London. A labour-led premium with materials near parity is consistent with that.
B28: Sources
B29: • | C29: Sectoral Employment Order (Construction Sector), Ireland — rates from 1 Aug 2026: Craftsperson €23.74, Category A €23.03, Category B €21.37, New Entrant €17.28.
B30: • | C30: CIJC Working Rule Agreement, UK — rates from 20 Jul 2026: Craft £16.40, Skill Rate 3 £14.07, General Operative £13.18.
B31: • | C31: GBP/EUR exchange rate, August 2026 — spot ~1.1694, 2026 YTD average 1.1562.
B32: • | C32: CSO Ireland Wholesale Price Index (building and construction materials) and UK building materials index — 3.2% vs 6.0% year-on-year to June 2026.
B33: • | C33: Arcadis International Construction Costs 2025 — Dublin 9th, Bristol 8th, London 2nd of 100 locations.
B34: • | C34: SCSI Tender Price Index, February 2026 — Irish commercial construction inflation 3% in H1 2026.

Sheet Review Queue
A1: Review Queue — items needing a human check
A2: 131 of 3793 derived items. These are carried in 'Derived Rates' at the values shown; review before relying on them.
A4: Ref | B4: Page | C4: Class | D4: Section | E4: Sub-heading | F4: Item | G4: Unit | H4: Gang hrs | I4: Labour £ | J4: Plant £ | K4: Material £ | L4: Sub-contract £ | M4: UK COST £ | N4: Labour € | O4: Plant € | P4: Material € | Q4: Sub-contract € | R4: IRISH COST € | S4: Derivation basis | T4: Confidence | U4: Published rate £ (superseded) | V4: Variance £ | W4: Flag | X4: Derivation note
A5: 319 | B5: IMG_0069 | C5: CLASS C: GEOTECHNICAL AND OTHER SPECIALIST PROCESSES | D5: 05 DIAPHRAGM WALLS | F5: Establishment of standard plant and equipment including bentonite storage tanks and removal on completion | G5: item | I5: 0 | J5: 0 | K5: 0 | L5: 549099.11 | M5: 549099.11 | N5: 0 | O5: 0 | P5: 0 | Q5: 718843 | R5: 718843 | S5: All-in specialist rate | T5: All-in (not split) | U5: 549099.11 | V5: 0 | W5: Probable source error — verify | X5: Source publishes a specialist/sub-contract all-in rate; no labour/plant/material build-up exists to derive from. This is 28x the next highest item in the class (£19,700.58) and out of line with comparable rates in the same section — likely a mis-read digit in the source scan. Verify before use.
A6: 370 | B6: IMG_0070 | C6: CLASS C: GEOTECHNICAL AND OTHER SPECIALIST PROCESSES | D6: 08 VIBRO-FLOTATION AND DYNAMIC COMPACTION | E6: Vibro flotation | F6: Depth not exceeding 5 m | G6: m | H6: 0.6 | I6: 19.07 | J6: 56.33 | K6: 0 | L6: 2436.35 | M6: 2511.75 | N6: 29.91 | O6: 65.87 | P6: 0 | Q6: 3189.5 | R6: 3285.29 | S6: Stated components + specialist balance | T6: Medium | U6: 2511.75 | V6: 0 | W6: Large unexplained balance | X6: Published plant/labour retained; the £2,436.35 balance of the specialist all-in rate is not broken down in the source.
A7: 371 | B7: IMG_0070 | C7: CLASS C: GEOTECHNICAL AND OTHER SPECIALIST PROCESSES | D7: 08 VIBRO-FLOTATION AND DYNAMIC COMPACTION | E7: Vibro flotation | F7: Depth: 5 m-10 m | G7: m | H7: 1.5 | I7: 47.69 | J7: 29.8 | K7: 0 | L7: 3070.38 | M7: 3147.87 | N7: 74.81 | O7: 34.85 | P7: 0 | Q7: 4019.53 | R7: 4129.19 | S7: Stated components + specialist balance | T7: Medium | U7: 3147.87 | V7: 0 | W7: Large unexplained balance | X7: Published plant/labour retained; the £3,070.38 balance of the specialist all-in rate is not broken down in the source.
A8: 372 | B8: IMG_0070 | C8: CLASS C: GEOTECHNICAL AND OTHER SPECIALIST PROCESSES | D8: 08 VIBRO-FLOTATION AND DYNAMIC COMPACTION | E8: Vibro flotation | F8: Depth: 10 m-20 m | G8: m | H8: 1.5 | I8: 47.69 | J8: 53.89 | K8: 0 | L8: 4283.89 | M8: 4385.47 | N8: 74.81 | O8: 63.02 | P8: 0 | Q8: 5608.18 | R8: 5746 | S8: Stated components + specialist balance | T8: Medium | U8: 4385.47 | V8: 0 | W8: Large unexplained balance | X8: Published plant/labour retained; the £4,283.89 balance of the specialist all-in rate is not broken down in the source.
A9: 373 | B9: IMG_0070 | C9: CLASS C: GEOTECHNICAL AND OTHER SPECIALIST PROCESSES | D9: 08 VIBRO-FLOTATION AND DYNAMIC COMPACTION | E9: Vibro flotation | F9: Depth: 30 m-40 m | G9: m | H9: 3 | I9: 95.37 | J9: 59.59 | K9: 0 | L9: 6924.55 | M9: 7079.51 | N9: 149.6 | O9: 69.68 | P9: 0 | Q9: 9065.15 | R9: 9284.43 | S9: Stated components + specialist balance | T9: Medium | U9: 7079.51 | V9: 0 | W9: Large unexplained balance | X9: Published plant/labour retained; the £6,924.55 balance of the specialist all-in rate is not broken down in the source.
A10: 589 | B10: IMG_0073 | C10: CLASS E: EARTHWORKS | D10: 01 EXCAVATION BY DREDGING | E10: In tidal locations, creating new channels on approaches to quays and similar locations or within dock systems | F10: approximate daily cost of backhoe dredger and two hopper barges £12,500; average production 100 m3/hr, 1,500 m3/day; locate, load, deposit and relocate | G10: m3 | I10: 4.13 | J10: 8.71 | K10: 0 | L10: 0 | M10: 12.84 | N10: 6.48 | O10: 10.19 | P10: 0 | Q10: 0 | R10: 16.66 | S10: Apportioned (class) | T10: Low | U10: 12.84 | V10: 0 | W10: Apportioned at class level | X10: Split from published rate using median L/P/M shares of 306 comparable build-ups at class level (32/68/0).
A11: 592 | B11: IMG_0073 | C11: CLASS E: EARTHWORKS | D11: 01 EXCAVATION BY DREDGING | E11: For general bed lowering or in maintaining shipping channels in rivers, estuaries or deltas | F11: locate, load, deposit and relocate | G11: tonne | I11: 1.67 | J11: 3.53 | K11: 0 | L11: 0 | M11: 5.2 | N11: 2.62 | O11: 4.13 | P11: 0 | Q11: 0 | R11: 6.75 | S11: Apportioned (class) | T11: Low | U11: 5.2 | V11: 0 | W11: Apportioned at class level | X11: Split from published rate using median L/P/M shares of 306 comparable build-ups at class level (32/68/0).
A12: 595 | B12: IMG_0073 | C12: CLASS E: EARTHWORKS | D12: 01 EXCAVATION BY DREDGING | E12: Harbour bed control | F12: average pumping capacity of silt/sand type materials containing maximum 30% volume of solids would be about 8,000 m3/day based on 24 hour working. Daily cost (hire basis) in the region of £20,000 including all floating equipment and discharge pipes, maintenance and all labour and plant to service but excluding mobilization/ initial set-up and demobilization costs (minimum £10,000). | G12: m3 | I12: 1.54 | J12: 3.25 | K12: 0 | L12: 0 | M12: 4.79 | N12: 2.42 | O12: 3.8 | P12: 0 | Q12: 0 | R12: 6.22 | S12: Apportioned (class) | T12: Low | U12: 4.79 | V12: 0 | W12: Apportioned at class level | X12: Split from published rate using median L/P/M shares of 306 comparable build-ups at class level (32/68/0).
A13: 598 | B13: IMG_0073 | C13: CLASS E: EARTHWORKS | D13: 01 EXCAVATION BY DREDGING | E13: For use in lakes, canals, rivers, industrial lagoons and from silted locations in dock systems | F13: average pumping output 30 m3 per hour and approximate average costs (excluding mobilization and demobilization costs ranging between £3,000 and £6,000 apiece) | G13: m3 | I13: 2.84 | J13: 5.97 | K13: 0 | L13: 0 | M13: 8.81 | N13: 4.45 | O13: 6.98 | P13: 0 | Q13: 0 | R13: 11.44 | S13: Apportioned (class) | T13: Low | U13: 8.81 | V13: 0 | W13: Apportioned at class level | X13: Split from published rate using median L/P/M shares of 306 comparable build-ups at class level (32/68/0).
A14: 1713 | B14: IMG_0090 | C14: CLASS H: PRECAST CONCRETE | D14: 02 PRESTRESSED PRE-TENSIONED BEAMS | E14: Bridge beams; Inverted 'T' Beams, flange width 495 mm | F14: section T1; 8 m long, 380 mm deep; mass 1.88t | G14: nr | I14: 845.93 | J14: 0 | K14: 974.65 | L14: 0 | M14: 1820.58 | N14: 1326.95 | O14: 0 | P14: 1139.76 | Q14: 0 | R14: 2466.71 | S14: Apportioned (class) | T14: Low | U14: 1820.58 | V14: 0 | W14: Apportioned at class level | X14: Split from published rate using median L/P/M shares of 19 comparable build-ups at class level (46/0/54).
A15: 1714 | B15: IMG_0090 | C15: CLASS H: PRECAST CONCRETE | D15: 02 PRESTRESSED PRE-TENSIONED BEAMS | E15: Bridge beams; Inverted 'T' Beams, flange width 495 mm | F15: section T2; 9 m long, 420 mm deep; mass 2.29t | G15: nr | I15: 1042.66 | J15: 0 | K15: 1201.3 | L15: 0 | M15: 2243.96 | N15: 1635.55 | O15: 0 | P15: 1404.8 | Q15: 0 | R15: 3040.35 | S15: Apportioned (class) | T15: Low | U15: 2243.96 | V15: 0 | W15: Apportioned at class level | X15: Split from published rate using median L/P/M shares of 19 comparable build-ups at class level (46/0/54).
A16: 1715 | B16: IMG_0090 | C16: CLASS H: PRECAST CONCRETE | D16: 02 PRESTRESSED PRE-TENSIONED BEAMS | E16: Bridge beams; Inverted 'T' Beams, flange width 495 mm | F16: section T3; 11 m long, 535 mm deep; mass 3.02t | G16: nr | I16: 1229.55 | J16: 0 | K16: 1416.63 | L16: 0 | M16: 2646.18 | N16: 1928.71 | O16: 0 | P16: 1656.61 | Q16: 0 | R16: 3585.32 | S16: Apportioned (class) | T16: Low | U16: 2646.18 | V16: 0 | W16: Apportioned at class level | X16: Split from published rate using median L/P/M shares of 19 comparable build-ups at class level (46/0/54).
A17: 1716 | B17: IMG_0090 | C17: CLASS H: PRECAST CONCRETE | D17: 02 PRESTRESSED PRE-TENSIONED BEAMS | E17: Bridge beams; Inverted 'T' Beams, flange width 495 mm | F17: section T4; 12 m long, 575 mm deep; mass 3.54t | G17: nr | I17: 1278.74 | J17: 0 | K17: 1473.31 | L17: 0 | M17: 2752.05 | N17: 2005.87 | O17: 0 | P17: 1722.89 | Q17: 0 | R17: 3728.76 | S17: Apportioned (class) | T17: Low | U17: 2752.05 | V17: 0 | W17: Apportioned at class level | X17: Split from published rate using median L/P/M shares of 19 comparable build-ups at class level (46/0/54).
A18: 1717 | B18: IMG_0090 | C18: CLASS H: PRECAST CONCRETE | D18: 02 PRESTRESSED PRE-TENSIONED BEAMS | E18: Bridge beams; Inverted 'T' Beams, flange width 495 mm | F18: section T5; 13 m long, 615 mm deep; mass 4.08t | G18: nr | I18: 1426.28 | J18: 0 | K18: 1643.3 | L18: 0 | M18: 3069.58 | N18: 2237.31 | O18: 0 | P18: 1921.68 | Q18: 0 | R18: 4158.99 | S18: Apportioned (class) | T18: Low | U18: 3069.58 | V18: 0 | W18: Apportioned at class level | X18: Split from published rate using median L/P/M shares of 19 comparable build-ups at class level (46/0/54).
A19: 1718 | B19: IMG_0090 | C19: CLASS H: PRECAST CONCRETE | D19: 02 PRESTRESSED PRE-TENSIONED BEAMS | E19: Bridge beams; Inverted 'T' Beams, flange width 495 mm | F19: section T6; 13 m long, 655 mm deep; mass 4.33t | G19: nr | I19: 1426.29 | J19: 0 | K19: 1643.31 | L19: 0 | M19: 3069.6 | N19: 2237.33 | O19: 0 | P19: 1921.69 | Q19: 0 | R19: 4159.01 | S19: Apportioned (class) | T19: Low | U19: 3069.6 | V19: 0 | W19: Apportioned at class level | X19: Split from published rate using median L/P/M shares of 19 comparable build-ups at class level (46/0/54).
A20: 1719 | B20: IMG_0090 | C20: CLASS H: PRECAST CONCRETE | D20: 02 PRESTRESSED PRE-TENSIONED BEAMS | E20: Bridge beams; Inverted 'T' Beams, flange width 495 mm | F20: section T7; 14 m long, 695 mm deep; mass 4.95t | G20: nr | I20: 1524.65 | J20: 0 | K20: 1756.64 | L20: 0 | M20: 3281.29 | N20: 2391.62 | O20: 0 | P20: 2054.21 | Q20: 0 | R20: 4445.83 | S20: Apportioned (class) | T20: Low | U20: 3281.29 | V20: 0 | W20: Apportioned at class level | X20: Split from published rate using median L/P/M shares of 19 comparable build-ups at class level (46/0/54).
A21: 1720 | B21: IMG_0090 | C21: CLASS H: PRECAST CONCRETE | D21: 02 PRESTRESSED PRE-TENSIONED BEAMS | E21: Bridge beams; Inverted 'T' Beams, flange width 495 mm | F21: section T8; 15 m long, 735 mm deep; mass 5.60t | G21: nr | I21: 1721.38 | J21: 0 | K21: 1983.29 | L21: 0 | M21: 3704.67 | N21: 2700.21 | O21: 0 | P21: 2319.26 | Q21: 0 | R21: 5019.47 | S21: Apportioned (class) | T21: Low | U21: 3704.67 | V21: 0 | W21: Apportioned at class level | X21: Split from published rate using median L/P/M shares of 19 comparable build-ups at class level (46/0/54).
... A124: 4431 | B124: IMG_0125 | C124: CLASS Q: PILING ANCILLARIES | D124: 08 PILE TESTS | E124: Pile tests; 430 mm dia. working pile; maximum test load of 1125kN using non-working tension piles as reaction; subsequent piles | F124: Make cure and test concrete cubes | G124: nr | I124: 0 | J124: 0 | K124: 0 | L124: 15.94 | M124: 15.94 | N124: 0 | O124: 0 | P124: 0 | Q124: 20.87 | R124: 20.87 | S124: All-in specialist rate | T124: All-in (not split) | U124: 15.94 | V124: 0 | W124: Outlier vs comparable items | X124: Source publishes a specialist/sub-contract all-in rate; no labour/plant/material build-up exists to derive from. Derived cost is far from the median of comparable items in this group (£1,170.81) — check the source figure.
A125: 4883 | B125: IMG_0131 | C125: CLASS R: ROADS AND PAVINGS | D125: 08 ANCILLARIES | E125: Standard reflectorized traffic signs | F125: extra for fixing singly to one face only | G125: nr | H125: 0.01 | I125: 1.14 | J125: 0.63 | K125: 0 | L125: 0 | M125: 1.77 | N125: 1.79 | O125: 0.74 | P125: 0 | Q125: 0 | R125: 2.52 | S125: Stated build-up | T125: High | U125: 1.78 | V125: -0.01 | W125: Outlier vs comparable items | X125: Labour + plant + material as published; reconciles to the published rate. Derived cost is far from the median of comparable items in this group (£71.87) — check the source figure.
A126: 4891 | B126: IMG_0131 | C126: CLASS R: ROADS AND PAVINGS | D126: 08 ANCILLARIES | E126: Standard two post signs; 1200 x 400 mm | F126: extra for fixing singly to one face only | G126: nr | H126: 0.02 | I126: 2.28 | J126: 1.32 | K126: 0 | L126: 0 | M126: 3.6 | N126: 3.58 | O126: 1.54 | P126: 0 | Q126: 0 | R126: 5.12 | S126: Stated build-up | T126: High | U126: 3.6 | V126: 0 | W126: Outlier vs comparable items | X126: Labour + plant + material as published; reconciles to the published rate. Derived cost is far from the median of comparable items in this group (£175.15) — check the source figure.
A127: 5252 | B127: IMG_0137 | C127: CLASS T: TUNNELS | D127: 03 IN SITU LINING TO SHAFTS | E127: Constructed in situ concrete | F127: Provision of complete standard shaft in in situ concrete; including piling, walls, floors, roof, drainage, finishes etc. | G127: nr | I127: 0 | J127: 0 | K127: 0 | L127: 50182994 | M127: 50182994 | N127: 0 | O127: 0 | P127: 0 | Q127: 65696143 | R127: 65696143 | S127: All-in specialist rate | T127: All-in (not split) | U127: 50182994 | V127: 0 | W127: Probable source error — verify | X127: Source publishes a specialist/sub-contract all-in rate; no labour/plant/material build-up exists to derive from. This is 20x the next highest item in the class (£2,534,723.45) and out of line with comparable rates in the same section — likely a mis-read digit in the source scan. Verify before use.
A128: 5266 | B128: IMG_0137 | C128: CLASS T: TUNNELS | D128: 03 IN SITU LINING TO SHAFTS | E128: Depressurization allowances | F128: Depressurization measures allowances | G128: nr | I128: 0 | J128: 0 | K128: 0 | L128: 752744.9 | M128: 752744.9 | N128: 0 | O128: 0 | P128: 0 | Q128: 985442.14 | R128: 985442.14 | S128: All-in specialist rate | T128: All-in (not split) | U128: 752744.9 | V128: 0 | W128: High value — verify | X128: Source publishes a specialist/sub-contract all-in rate; no labour/plant/material build-up exists to derive from. Unit rate of £250,000 or more — plausible for major specialist works but worth verifying against the source.
A129: 5339 | B129: IMG_0138 | C129: CLASS T: TUNNELS | D129: 09 VIADUCTS | E129: Permanent casings each length | F129: In situ Reinforced Concrete Piers on piles; off shore standard vertical pier | G129: nr | I129: 0 | J129: 0 | K129: 0 | L129: 646688.97 | M129: 646688.97 | N129: 0 | O129: 0 | P129: 0 | Q129: 846600.97 | R129: 846600.97 | S129: All-in specialist rate | T129: All-in (not split) | U129: 646688.97 | V129: 0 | W129: High value — verify | X129: Source publishes a specialist/sub-contract all-in rate; no labour/plant/material build-up exists to derive from. Unit rate of £250,000 or more — plausible for major specialist works but worth verifying against the source.
A130: 5340 | B130: IMG_0138 | C130: CLASS T: TUNNELS | D130: 09 VIADUCTS | E130: Permanent casings each length | F130: V shaped pier | G130: nr | I130: 0 | J130: 0 | K130: 0 | L130: 2534723.5 | M130: 2534723.5 | N130: 0 | O130: 0 | P130: 0 | Q130: 3318286.6 | R130: 3318286.6 | S130: All-in specialist rate | T130: All-in (not split) | U130: 2534723.5 | V130: 0 | W130: High value — verify | X130: Source publishes a specialist/sub-contract all-in rate; no labour/plant/material build-up exists to derive from. Unit rate of £250,000 or more — plausible for major specialist works but worth verifying against the source.
A131: 5341 | B131: IMG_0138 | C131: CLASS T: TUNNELS | D131: 09 VIADUCTS | E131: Permanent casings each length | F131: fixed buttress 3 legs pier | G131: nr | I131: 0 | J131: 0 | K131: 0 | L131: 1189313.1 | M131: 1189313.1 | N131: 0 | O131: 0 | P131: 0 | Q131: 1556967.3 | R131: 1556967.3 | S131: All-in specialist rate | T131: All-in (not split) | U131: 1189313.1 | V131: 0 | W131: High value — verify | X131: Source publishes a specialist/sub-contract all-in rate; no labour/plant/material build-up exists to derive from. Unit rate of £250,000 or more — plausible for major specialist works but worth verifying against the source.
A132: 5343 | B132: IMG_0138 | C132: CLASS T: TUNNELS | D132: 09 VIADUCTS | E132: In situ Reinforced Concrete Piers on piles; on shore | F132: standard vertical pier | G132: nr | I132: 0 | J132: 0 | K132: 0 | L132: 624389.35 | M132: 624389.35 | N132: 0 | O132: 0 | P132: 0 | Q132: 817407.83 | R132: 817407.83 | S132: All-in specialist rate | T132: All-in (not split) | U132: 624389.35 | V132: 0 | W132: High value — verify | X132: Source publishes a specialist/sub-contract all-in rate; no labour/plant/material build-up exists to derive from. Unit rate of £250,000 or more — plausible for major specialist works but worth verifying against the source.
A133: 5344 | B133: IMG_0138 | C133: CLASS T: TUNNELS | D133: 09 VIADUCTS | E133: In situ Reinforced Concrete Piers on piles; on shore | F133: fixed vertical pier | G133: nr | I133: 0 | J133: 0 | K133: 0 | L133: 1273456.9 | M133: 1273456.9 | N133: 0 | O133: 0 | P133: 0 | Q133: 1667122.7 | R133: 1667122.7 | S133: All-in specialist rate | T133: All-in (not split) | U133: 1273456.9 | V133: 0 | W133: High value — verify | X133: Source publishes a specialist/sub-contract all-in rate; no labour/plant/material build-up exists to derive from. Unit rate of £250,000 or more — plausible for major specialist works but worth verifying against the source.
A134: 5345 | B134: IMG_0138 | C134: CLASS T: TUNNELS | D134: 09 VIADUCTS | E134: In situ Reinforced Concrete Piers on piles; on shore | F134: expansion buttress pier | G134: nr | I134: 0 | J134: 0 | K134: 0 | L134: 859362.22 | M134: 859362.22 | N134: 0 | O134: 0 | P134: 0 | Q134: 1125018.2 | R134: 1125018.2 | S134: All-in specialist rate | T134: All-in (not split) | U134: 859362.22 | V134: 0 | W134: High value — verify | X134: Source publishes a specialist/sub-contract all-in rate; no labour/plant/material build-up exists to derive from. Unit rate of £250,000 or more — plausible for major specialist works but worth verifying against the source.
A135: 5346 | B135: IMG_0138 | C135: CLASS T: TUNNELS | D135: 09 VIADUCTS | E135: In situ Reinforced Concrete Piers on piles; on shore | F135: fixed buttress 3 legs pier | G135: nr | I135: 0 | J135: 0 | K135: 0 | L135: 1184853.1 | M135: 1184853.1 | N135: 0 | O135: 0 | P135: 0 | Q135: 1551128.7 | R135: 1551128.7 | S135: All-in specialist rate | T135: All-in (not split) | U135: 1184853.1 | V135: 0 | W135: High value — verify | X135: Source publishes a specialist/sub-contract all-in rate; no labour/plant/material build-up exists to derive from. Unit rate of £250,000 or more — plausible for major specialist works but worth verifying against the source.

Sheet Resource Rates
A1: Resource Rates — labour gang and plant build-ups
A2: The hourly labour-gang and plant rates published in the source. These are cost INPUTS, not priceable items, and are excluded from 'Derived Rates'. Rows reading 'Total Gang Rate/Hour' or 'Total Rate/Hour' are the composite rates.
A4: Ref | B4: Page | C4: Class | D4: Resource type | E4: Gang / plant spread | F4: Resource | G4: Labour £/hr | H4: Plant £/hr | I4: Material £
A5: 107 | B5: IMG_0066 | C5: CLASS B: GROUND INVESTIGATION | D5: RESOURCES - LABOUR | E5: Labour Gang Build-up Rate; Trial hole gang | F5: 1 ganger or chargehand (skill rate 4) | G5: 31.39
A6: 108 | B6: IMG_0066 | C6: CLASS B: GROUND INVESTIGATION | D6: RESOURCES - LABOUR | E6: Labour Gang Build-up Rate; Trial hole gang | F6: 1 skilled operative (skill rate 4) | G6: 29.49
A7: 109 | B7: IMG_0066 | C7: CLASS B: GROUND INVESTIGATION | D7: RESOURCES - LABOUR | E7: Labour Gang Build-up Rate; Trial hole gang | F7: 2 unskilled operatives (general) | G7: 49.35
A8: 110 | B8: IMG_0066 | C8: CLASS B: GROUND INVESTIGATION | D8: RESOURCES - LABOUR | E8: Labour Gang Build-up Rate; Trial hole gang | F8: 1 plant operator (skill rate 3) | G8: 38.96
A9: 111 | B9: IMG_0066 | C9: CLASS B: GROUND INVESTIGATION | D9: RESOURCES - LABOUR | E9: Labour Gang Build-up Rate; Trial hole gang | F9: Total Gang Rate/Hour | G9: 135.41
A10: 114 | B10: IMG_0066 | C10: CLASS B: GROUND INVESTIGATION | D10: RESOURCES - PLANT | E10: Plant Resources Build-up Rate; Trial holes | F10: 8 tonne wheeled backacter | H10: 72.4
A11: 115 | B11: IMG_0066 | C11: CLASS B: GROUND INVESTIGATION | D11: RESOURCES - PLANT | E11: Plant Resources Build-up Rate; Trial holes | F11: 3 tonne dumper | H11: 21.07
A12: 116 | B12: IMG_0066 | C12: CLASS B: GROUND INVESTIGATION | D12: RESOURCES - PLANT | E12: Plant Resources Build-up Rate; Trial holes | F12: 3.7 m3/min compressor, 2 tool | H12: 21.22
A13: 117 | B13: IMG_0066 | C13: CLASS B: GROUND INVESTIGATION | D13: RESOURCES - PLANT | E13: Plant Resources Build-up Rate; Trial holes | F13: two 2.4 m3/min road breakers | H13: 16.6
A14: 118 | B14: IMG_0066 | C14: CLASS B: GROUND INVESTIGATION | D14: RESOURCES - PLANT | E14: Plant Resources Build-up Rate; Trial holes | F14: extra 50 ft / 15 m hose | H14: 0.53
A15: 119 | B15: IMG_0066 | C15: CLASS B: GROUND INVESTIGATION | D15: RESOURCES - PLANT | E15: Plant Resources Build-up Rate; Trial holes | F15: plate compactors; vibrating compaction; plate 180 kg/ 600 mm | H15: 4.92
A16: 120 | B16: IMG_0066 | C16: CLASS B: GROUND INVESTIGATION | D16: RESOURCES - PLANT | E16: Plant Resources Build-up Rate; Trial holes | F16: Total Rate/Hour | H16: 136.73
A17: 527 | B17: IMG_0072 | C17: CLASS E: EARTHWORKS | D17: RESOURCES - LABOUR | E17: Labour Gang Build-up Rates; Excavation for cuttings gang | F17: 1 plant operator (skill rate 1) - 33% of time | G17: 17.5
A18: 528 | B18: IMG_0072 | C18: CLASS E: EARTHWORKS | D18: RESOURCES - LABOUR | E18: Labour Gang Build-up Rates; Excavation for cuttings gang | F18: 1 plant operator (skill rate 2) - 66% of time | G18: 29.63
A19: 529 | B19: IMG_0072 | C19: CLASS E: EARTHWORKS | D19: RESOURCES - LABOUR | E19: Labour Gang Build-up Rates; Excavation for cuttings gang | F19: 1 banksman (skill rate 4) | G19: 29.49
A20: 530 | B20: IMG_0072 | C20: CLASS E: EARTHWORKS | D20: RESOURCES - LABOUR | E20: Labour Gang Build-up Rates; Excavation for cuttings gang | F20: Total Gang Rate/Hour | G20: 73.78
A21: 532 | B21: IMG_0072 | C21: CLASS E: EARTHWORKS | D21: RESOURCES - LABOUR | E21: Excavation for foundations gang | F21: 1 plant operator (skill rate 3) - 33% of time | G21: 12.86
A22: 533 | B22: IMG_0072 | C22: CLASS E: EARTHWORKS | D22: RESOURCES - LABOUR | E22: Excavation for foundations gang | F22: 1 plant operator (skill rate 2) - 66% of time | G22: 29.63
A23: 534 | B23: IMG_0072 | C23: CLASS E: EARTHWORKS | D23: RESOURCES - LABOUR | E23: Excavation for foundations gang | F23: 1 banksman (skill rate 4) | G23: 29.49
A24: 535 | B24: IMG_0072 | C24: CLASS E: EARTHWORKS | D24: RESOURCES - LABOUR | E24: Excavation for foundations gang | F24: Total Gang Rate/Hour | G24: 65.53
A25: 537 | B25: IMG_0072 | C25: CLASS E: EARTHWORKS | D25: RESOURCES - LABOUR | E25: General excavation gang | F25: 1 plant operator (skill rate 3) | G25: 38.96
A26: 538 | B26: IMG_0072 | C26: CLASS E: EARTHWORKS | D26: RESOURCES - LABOUR | E26: General excavation gang | F26: 1 plant operator (skill rate 3) - 25% of time | G26: 9.74
A27: 539 | B27: IMG_0072 | C27: CLASS E: EARTHWORKS | D27: RESOURCES - LABOUR | E27: General excavation gang | F27: 1 banksman (skill rate 4) | G27: 29.49
A28: 540 | B28: IMG_0072 | C28: CLASS E: EARTHWORKS | D28: RESOURCES - LABOUR | E28: General excavation gang | F28: Total Gang Rate/Hour | G28: 69.76
... A46: 565 | B46: IMG_0073 | C46: CLASS E: EARTHWORKS | D46: RESOURCES - LABOUR | E46: Horticultural works gang | F46: Total Gang Rate/Hour | G46: 49
A47: 568 | B47: IMG_0073 | C47: CLASS E: EARTHWORKS | D47: RESOURCES - PLANT | E47: Plant Resources Build-up Rate; Excavation for foundations | F47: hydraulic Backacter - 21 tonne (33% of time) | H47: 39
A48: 569 | B48: IMG_0073 | C48: CLASS E: EARTHWORKS | D48: RESOURCES - PLANT | E48: Plant Resources Build-up Rate; Excavation for foundations | F48: hydraulic Backacter - 14.5 tonne (33% of time) | H48: 32.18
A49: 570 | B49: IMG_0073 | C49: CLASS E: EARTHWORKS | D49: RESOURCES - PLANT | E49: Plant Resources Build-up Rate; Excavation for foundations | F49: 1000 kg hydraulic breaker (33% of time) | H49: 10.03
A50: 571 | B50: IMG_0073 | C50: CLASS E: EARTHWORKS | D50: RESOURCES - PLANT | E50: Plant Resources Build-up Rate; Excavation for foundations | F50: tractor loader - 0.80 m3 (33% of time) | H50: 26.11
A51: 572 | B51: IMG_0073 | C51: CLASS E: EARTHWORKS | D51: RESOURCES - PLANT | E51: Plant Resources Build-up Rate; Excavation for foundations | F51: Total Rate/Hour | H51: 107.32
A52: 574 | B52: IMG_0073 | C52: CLASS E: EARTHWORKS | D52: RESOURCES - PLANT | E52: Filling | F52: 1.5 m3 tractor loader | H52: 132.28
A53: 575 | B53: IMG_0073 | C53: CLASS E: EARTHWORKS | D53: RESOURCES - PLANT | E53: Filling | F53: 6t vibratory roller | H53: 50.62
A54: 576 | B54: IMG_0073 | C54: CLASS E: EARTHWORKS | D54: RESOURCES - PLANT | E54: Filling | F54: pedestrian Roller, Bomag BW35 | H54: 10.84
A55: 577 | B55: IMG_0073 | C55: CLASS E: EARTHWORKS | D55: RESOURCES - PLANT | E55: Filling | F55: Total Rate/Hour | H55: 193.74
A56: 579 | B56: IMG_0073 | C56: CLASS E: EARTHWORKS | D56: RESOURCES - PLANT | E56: Treatment of filled surfaces | F56: 1.5 m3 tractor loader | H56: 132.28
A57: 580 | B57: IMG_0073 | C57: CLASS E: EARTHWORKS | D57: RESOURCES - PLANT | E57: Treatment of filled surfaces | F57: pedestrian Roller, Bomag BW35 | H57: 10.84
A58: 581 | B58: IMG_0073 | C58: CLASS E: EARTHWORKS | D58: RESOURCES - PLANT | E58: Treatment of filled surfaces | F58: Total Rate/Hour | H58: 143.11
... A60: 584 | B60: IMG_0073 | C60: CLASS E: EARTHWORKS | D60: RESOURCES - PLANT | E60: Geotextiles (heavy sheets) | F60: Total Rate/Hour | H60: 132.28
A61: 1050 | B61: IMG_0080 | C61: CLASS F: IN SITU CONCRETE | D61: RESOURCES - LABOUR | E61: Labour Gang Build-up Rates; Concrete gang | F61: 1 ganger or chargehand (skill rate 4) | G61: 31.39
A62: 1051 | B62: IMG_0080 | C62: CLASS F: IN SITU CONCRETE | D62: RESOURCES - LABOUR | E62: Labour Gang Build-up Rates; Concrete gang | F62: 2 skilled operatives (skill rate 4) | G62: 58.99
A63: 1052 | B63: IMG_0080 | C63: CLASS F: IN SITU CONCRETE | D63: RESOURCES - LABOUR | E63: Labour Gang Build-up Rates; Concrete gang | F63: 4 unskilled operatives (general) | G63: 98.7
A64: 1053 | B64: IMG_0080 | C64: CLASS F: IN SITU CONCRETE | D64: RESOURCES - LABOUR | E64: Labour Gang Build-up Rates; Concrete gang | F64: 1 plant operator (skill rate 3) - 25% of time | G64: 9.74
A65: 1054 | B65: IMG_0080 | C65: CLASS F: IN SITU CONCRETE | D65: RESOURCES - LABOUR | E65: Labour Gang Build-up Rates; Concrete gang | F65: Total Gang Rate/Hour | G65: 181.61
A66: 1058 | B66: IMG_0080 | C66: CLASS F: IN SITU CONCRETE | D66: RESOURCES - MATERIAL | E66: Material Resources Build-up Rate | F66: delivery to site for each additional mile from the concrete plant further than 5 miles (8 km) | I66: 3.51
A67: 1059 | B67: IMG_0080 | C67: CLASS F: IN SITU CONCRETE | D67: RESOURCES - MATERIAL | E67: Material Resources Build-up Rate | F67: mix design, per trial mix | I67: 392.73
A68: 1060 | B68: IMG_0080 | C68: CLASS F: IN SITU CONCRETE | D68: RESOURCES - MATERIAL | E68: Material Resources Build-up Rate | F68: part loads, per m3 below full load | I68: 44.07
A69: 1061 | B69: IMG_0080 | C69: CLASS F: IN SITU CONCRETE | D69: RESOURCES - MATERIAL | E69: Material Resources Build-up Rate | F69: waiting time (in excess of 6 mins/m3 'norm' discharge time) | I69: 136.26
A70: 1062 | B70: IMG_0080 | C70: CLASS F: IN SITU CONCRETE | D70: RESOURCES - MATERIAL | E70: Material Resources Build-up Rate | F70: making and testing concrete cube | G70: 16.98
A71: 1063 | B71: IMG_0080 | C71: CLASS F: IN SITU CONCRETE | D71: RESOURCES - MATERIAL | E71: Material Resources Build-up Rate | F71: pumping from ready mix truck to point of placing at the rate of 25 m3/hour | G71: 2.59 | H71: 9.65
A72: 1064 | B72: IMG_0080 | C72: CLASS F: IN SITU CONCRETE | D72: RESOURCES - MATERIAL | E72: Material Resources Build-up Rate | F72: pumping from ready mix truck to point of placing at the rate of 45 m3/hour | G72: 1.25 | H72: 10.17
A73: 1067 | B73: IMG_0080 | C73: CLASS F: IN SITU CONCRETE | D73: RESOURCES - PLANT | E73: Plant Resources Build-up Rate; Concrete | F73: 10t Crane (50% of time) | H73: 41.34
A74: 1068 | B74: IMG_0080 | C74: CLASS F: IN SITU CONCRETE | D74: RESOURCES - PLANT | E74: Plant Resources Build-up Rate; Concrete | F74: 1.00 m3 concrete skip (50% of time) | H74: 2.6
A75: 1069 | B75: IMG_0080 | C75: CLASS F: IN SITU CONCRETE | D75: RESOURCES - PLANT | E75: Plant Resources Build-up Rate; Concrete | F75: 11.30 m3/min compressor, 2 tool | H75: 83.24
A76: 1070 | B76: IMG_0080 | C76: CLASS F: IN SITU CONCRETE | D76: RESOURCES - PLANT | E76: Plant Resources Build-up Rate; Concrete | F76: four 54 mm poker vibrators | H76: 9.55
A77: 1071 | B77: IMG_0080 | C77: CLASS F: IN SITU CONCRETE | D77: RESOURCES - PLANT | E77: Plant Resources Build-up Rate; Concrete | F77: Total Rate/Hour | H77: 136.73
A78: 1275 | B78: IMG_0083 | C78: CLASS G: CONCRETE ANCILLARIES | D78: RESOURCES - LABOUR | E78: Labour Resources Build-up Rate; Formwork gang - small areas | F78: 1 joiner (craftsman) | G78: 33.9
A79: 1276 | B79: IMG_0083 | C79: CLASS G: CONCRETE ANCILLARIES | D79: RESOURCES - LABOUR | E79: Labour Resources Build-up Rate; Formwork gang - small areas | F79: 1 unskilled operative (general) | G79: 24.68
A80: 1277 | B80: IMG_0083 | C80: CLASS G: CONCRETE ANCILLARIES | D80: RESOURCES - LABOUR | E80: Labour Resources Build-up Rate; Formwork gang - small areas | F80: Total Gang Rate/Hour | G80: 56.31
A81: 1279 | B81: IMG_0083 | C81: CLASS G: CONCRETE ANCILLARIES | D81: RESOURCES - LABOUR | E81: Formwork gang - large areas | F81: 1 foreman joiner (craftsman) | G81: 33.9
A82: 1280 | B82: IMG_0083 | C82: CLASS G: CONCRETE ANCILLARIES | D82: RESOURCES - LABOUR | E82: Formwork gang - large areas | F82: 2 joiners (craftsman) | G82: 58.99
A83: 1281 | B83: IMG_0083 | C83: CLASS G: CONCRETE ANCILLARIES | D83: RESOURCES - LABOUR | E83: Formwork gang - large areas | F83: 1 unskilled operative (general) | G83: 24.68
A84: 1282 | B84: IMG_0083 | C84: CLASS G: CONCRETE ANCILLARIES | D84: RESOURCES - LABOUR | E84: Formwork gang - large areas | F84: Total Gang Rate/Hour | G84: 112.45
A85: 1284 | B85: IMG_0083 | C85: CLASS G: CONCRETE ANCILLARIES | D85: RESOURCES - LABOUR | E85: Reinforcement gang | F85: 1 foreman steel fixer (craftsman) | G85: 33.9
A86: 1285 | B86: IMG_0083 | C86: CLASS G: CONCRETE ANCILLARIES | D86: RESOURCES - LABOUR | E86: Reinforcement gang | F86: 4 steel fixers (craftsman) | G86: 117.98
A87: 1286 | B87: IMG_0083 | C87: CLASS G: CONCRETE ANCILLARIES | D87: RESOURCES - LABOUR | E87: Reinforcement gang | F87: 1 unskilled operative (general) | G87: 24.68
A88: 1287 | B88: IMG_0083 | C88: CLASS G: CONCRETE ANCILLARIES | D88: RESOURCES - LABOUR | E88: Reinforcement gang | F88: Total Gang Rate/Hour | G88: 168.59
A89: 1289 | B89: IMG_0083 | C89: CLASS G: CONCRETE ANCILLARIES | D89: RESOURCES - LABOUR | E89: Reinforcement - on-site bending/baling gang | F89: 1 steel fixer (craftsman) | G89: 29.49
... A99: 1301 | B99: IMG_0083 | C99: CLASS G: CONCRETE ANCILLARIES | D99: RESOURCES - LABOUR | E99: Concrete accessories gang | F99: Total Gang Rate/Hour | G99: 75.37
A100: 1305 | B100: IMG_0083 | C100: CLASS G: CONCRETE ANCILLARIES | D100: RESOURCES - MATERIAL | E100: Material Resources Build-up Rate; Reinforcement; supply only ex works materials rates | F100: Reinforcement; high tensile steel bars; straight; T12 | I100: 1150.73
A101: 1307 | B101: IMG_0083 | C101: CLASS G: CONCRETE ANCILLARIES | D101: RESOURCES - MATERIAL | E101: Material Resources Build-up Rate; Reinforcement; supply only ex works materials rates | F101: Stainless steel bars; straight | I101: 6277.35
A102: 1308 | B102: IMG_0083 | C102: CLASS G: CONCRETE ANCILLARIES | D102: RESOURCES - MATERIAL | E102: Material Resources Build-up Rate; Reinforcement; supply only ex works materials rates | F102: Stainless steel bars; bent | I102: 6277.35
A103: 1310 | B103: IMG_0083 | C103: CLASS G: CONCRETE ANCILLARIES | D103: RESOURCES - MATERIAL | E103: Welded fabric to BS 4483 in sheets 4.80 x 2.40 | F103: A98 | I103: 6.2
A104: 1311 | B104: IMG_0083 | C104: CLASS G: CONCRETE ANCILLARIES | D104: RESOURCES - MATERIAL | E104: Welded fabric to BS 4483 in sheets 4.80 x 2.40 | F104: A142 | I104: 5.1
A105: 1312 | B105: IMG_0083 | C105: CLASS G: CONCRETE ANCILLARIES | D105: RESOURCES - MATERIAL | E105: Welded fabric to BS 4483 in sheets 4.80 x 2.40 | F105: A193 | I105: 7.26
A106: 1313 | B106: IMG_0083 | C106: CLASS G: CONCRETE ANCILLARIES | D106: RESOURCES - MATERIAL | E106: Welded fabric to BS 4483 in sheets 4.80 x 2.40 | F106: A252 | I106: 8.04
A107: 1314 | B107: IMG_0083 | C107: CLASS G: CONCRETE ANCILLARIES | D107: RESOURCES - MATERIAL | E107: Welded fabric to BS 4483 in sheets 4.80 x 2.40 | F107: A393 | I107: 12.36
A108: 1315 | B108: IMG_0083 | C108: CLASS G: CONCRETE ANCILLARIES | D108: RESOURCES - MATERIAL | E108: Welded fabric to BS 4483 in sheets 4.80 x 2.40 | F108: B196 | I108: 13.58
A109: 1316 | B109: IMG_0083 | C109: CLASS G: CONCRETE ANCILLARIES | D109: RESOURCES - MATERIAL | E109: Welded fabric to BS 4483 in sheets 4.80 x 2.40 | F109: B283 | I109: 10.96
A110: 1317 | B110: IMG_0083 | C110: CLASS G: CONCRETE ANCILLARIES | D110: RESOURCES - MATERIAL | E110: Welded fabric to BS 4483 in sheets 4.80 x 2.40 | F110: B385 | I110: 11.7
A111: 1318 | B111: IMG_0083 | C111: CLASS G: CONCRETE ANCILLARIES | D111: RESOURCES - MATERIAL | E111: Welded fabric to BS 4483 in sheets 4.80 x 2.40 | F111: B503 | I111: 16.83
... A138: 1348 | B138: IMG_0084 | C138: CLASS G: CONCRETE ANCILLARIES | D138: RESOURCES - MATERIAL | E138: extra for threaded bar at factory | F138: 40 mm dia. | I138: 10.15
A139: 1351 | B139: IMG_0084 | C139: CLASS G: CONCRETE ANCILLARIES | D139: RESOURCES - PLANT | E139: Plant Resources Build-up Rate; Formwork - small areas | F139: 20t crawler crane - 50% of time | H139: 29.52
A140: 1352 | B140: IMG_0084 | C140: CLASS G: CONCRETE ANCILLARIES | D140: RESOURCES - PLANT | E140: Plant Resources Build-up Rate; Formwork - small areas | F140: 22" dia. saw bench | H140: 5.09
A141: 1353 | B141: IMG_0084 | C141: CLASS G: CONCRETE ANCILLARIES | D141: RESOURCES - PLANT | E141: Plant Resources Build-up Rate; Formwork - small areas | F141: allowance for small power tools | H141: 1.15
A142: 1354 | B142: IMG_0084 | C142: CLASS G: CONCRETE ANCILLARIES | D142: RESOURCES - PLANT | E142: Plant Resources Build-up Rate; Formwork - small areas | F142: Total Rate/Hour | H142: 35.77
A143: 1356 | B143: IMG_0084 | C143: CLASS G: CONCRETE ANCILLARIES | D143: RESOURCES - PLANT | E143: Formwork - large areas | F143: 20t crawler crane - 25% of time | H143: 14.76
A144: 1357 | B144: IMG_0084 | C144: CLASS G: CONCRETE ANCILLARIES | D144: RESOURCES - PLANT | E144: Formwork - large areas | F144: 22" dia. saw bench | H144: 5.09
A145: 1358 | B145: IMG_0084 | C145: CLASS G: CONCRETE ANCILLARIES | D145: RESOURCES - PLANT | E145: Formwork - large areas | F145: allowance for small power tools | H145: 1.15
A146: 1359 | B146: IMG_0084 | C146: CLASS G: CONCRETE ANCILLARIES | D146: RESOURCES - PLANT | E146: Formwork - large areas | F146: Total Rate/Hour | H146: 21.01
A147: 1361 | B147: IMG_0084 | C147: CLASS G: CONCRETE ANCILLARIES | D147: RESOURCES - PLANT | E147: Reinforcement | F147: 30 t crawler crane - 25% of time | H147: 15.47
A148: 1362 | B148: IMG_0084 | C148: CLASS G: CONCRETE ANCILLARIES | D148: RESOURCES - PLANT | E148: Reinforcement | F148: bar cropper | H148: 5.7
A149: 1363 | B149: IMG_0084 | C149: CLASS G: CONCRETE ANCILLARIES | D149: RESOURCES - PLANT | E149: Reinforcement | F149: small power tools | H149: 2.16
A150: 1364 | B150: IMG_0084 | C150: CLASS G: CONCRETE ANCILLARIES | D150: RESOURCES - PLANT | E150: Reinforcement | F150: support acrows, tirfors, kentledge, etc. | H150: 0.96
A151: 1365 | B151: IMG_0084 | C151: CLASS G: CONCRETE ANCILLARIES | D151: RESOURCES - PLANT | E151: Reinforcement | F151: Total Rate/Hour | H151: 24.29
A152: 1761 | B152: IMG_0091 | C152: CLASS I: PIPEWORK - PIPES | D152: RESOURCES - LABOUR | E152: Labour Resources Build-up Rate; Drainage/pipework gang (small bore) | F152: 1 ganger/chargehand (skill rate 4) - 50% of time
A153: 1762 | B153: IMG_0091 | C153: CLASS I: PIPEWORK - PIPES | D153: RESOURCES - LABOUR | E153: Labour Resources Build-up Rate; Drainage/pipework gang (small bore) | F153: 1 skilled operative (skill rate 4)
A154: 1763 | B154: IMG_0091 | C154: CLASS I: PIPEWORK - PIPES | D154: RESOURCES - LABOUR | E154: Labour Resources Build-up Rate; Drainage/pipework gang (small bore) | F154: 2 unskilled operatives (general)
...

Sheet Preliminaries (Excluded)
A1: Preliminaries — CESMM Class A: General Items (EXCLUDED from the derivation)
A2: Excluded as requested. Retained here unchanged so they can be brought back in later — preliminaries are normally priced as a project-level allowance rather than built into unit rates.
A4: Ref | B4: Page | C4: Class | D4: Section | E4: Sub-heading | F4: Item | G4: Unit | H4: Gang hrs | I4: Labour £ | J4: Plant £ | K4: Material £ | L4: Published rate £
A5: 19 | B5: IMG_0065 | C5: CLASS A: GENERAL ITEMS | D5: 03 METHOD RELATED CHARGES | E5: Transport vehicles | F5: 4 WD utility short wheelbase | G5: week | J5: 1369.23 | L5: 1369.23
A6: 20 | B6: IMG_0065 | C6: CLASS A: GENERAL ITEMS | D6: 03 METHOD RELATED CHARGES | E6: Transport vehicles | F6: 4 WD long wheelbase | G6: week | J6: 1206.77 | L6: 1206.77
A7: 25 | B7: IMG_0065 | C7: CLASS A: GENERAL ITEMS | D7: 03 METHOD RELATED CHARGES | E7: Attendance upon the Engineer's staff | F7: Driver | G7: week | H7: 40 | I7: 1192.13 | L7: 1192.13
A8: 26 | B8: IMG_0065 | C8: CLASS A: GENERAL ITEMS | D8: 03 METHOD RELATED CHARGES | E8: Attendance upon the Engineer's staff | F8: Chainmen | G8: week | H8: 40 | I8: 937.35 | L8: 937.35
A9: 27 | B9: IMG_0065 | C9: CLASS A: GENERAL ITEMS | D9: 03 METHOD RELATED CHARGES | E9: Attendance upon the Engineer's staff | F9: Laboratory assistants | G9: week | H9: 40 | I9: 1284.96 | L9: 1284.96
A10: 34 | B10: IMG_0065 | C10: CLASS A: GENERAL ITEMS | D10: METHOD RELATED CHARGES | E10: Offices; establishment and removal; Fixed Charge | F10: 80 m2 mobile unit (10 staff x 8 m2) | G10: item | J10: 2307.7 | L10: 2307.7
A11: 35 | B11: IMG_0065 | C11: CLASS A: GENERAL ITEMS | D11: METHOD RELATED CHARGES | E11: Offices; establishment and removal; Fixed Charge | F11: 10 m2 section units; two | G11: item | J11: 989.34 | L11: 989.34
A12: 37 | B12: IMG_0065 | C12: CLASS A: GENERAL ITEMS | D12: METHOD RELATED CHARGES | E12: Offices; maintaining; Time Related Charge | F12: 80 m2 mobile unit (10 staff x 8 m2) | G12: week | J12: 593.6 | L12: 593.6
A13: 38 | B13: IMG_0065 | C13: CLASS A: GENERAL ITEMS | D13: METHOD RELATED CHARGES | E13: Offices; maintaining; Time Related Charge | F13: 10 m2 section units; two | G13: week | J13: 329.77 | L13: 329.77
A14: 40 | B14: IMG_0065 | C14: CLASS A: GENERAL ITEMS | D14: METHOD RELATED CHARGES | E14: Stores; establishment and removal; Fixed Charge | F14: 22 m2 section unit | G14: item | J14: 791.46 | L14: 791.46
A15: 42 | B15: IMG_0065 | C15: CLASS A: GENERAL ITEMS | D15: METHOD RELATED CHARGES | E15: Stores; maintaining; Time Related Charge | F15: 22 m2 section unit | G15: item | J15: 131.93 | L15: 131.93
A16: 44 | B16: IMG_0065 | C16: CLASS A: GENERAL ITEMS | D16: METHOD RELATED CHARGES | E16: Canteens and messrooms; establishment and removal; Fixed Charge | F16: 70 m2 mobile unit (70 men) | G16: item | J16: 1978.65 | L16: 1978.65
A17: 46 | B17: IMG_0065 | C17: CLASS A: GENERAL ITEMS | D17: METHOD RELATED CHARGES | E17: Canteens and messrooms; maintaining; Time Related Charge | F17: 70 m2 mobile unit (70 men) | G17: week | J17: 560.61 | L17: 560.61
A18: 50 | B18: IMG_0065 | C18: CLASS A: GENERAL ITEMS | D18: METHOD RELATED CHARGES | E18: Transport | F18: wheeled tractor including driver | G18: week | H18: 40 | I18: 987 | J18: 1613.17 | L18: 2600.17
A19: 51 | B19: IMG_0065 | C19: CLASS A: GENERAL ITEMS | D19: METHOD RELATED CHARGES | E19: Transport | F19: trailer | G19: week | J19: 25.83 | L19: 25.83
A20: 53 | B20: IMG_0065 | C20: CLASS A: GENERAL ITEMS | D20: METHOD RELATED CHARGES | E20: Tractor | F20: hire charge | G20: week | J20: 890.5 | L20: 890.5
A21: 54 | B21: IMG_0065 | C21: CLASS A: GENERAL ITEMS | D21: METHOD RELATED CHARGES | E21: Tractor | F21: driver (skill rate 4) | G21: week | H21: 40 | I21: 1269.7 | L21: 1269.7
A22: 55 | B22: IMG_0065 | C22: CLASS A: GENERAL ITEMS | D22: METHOD RELATED CHARGES | E22: Tractor | F22: fuel and consumables | G22: week | J22: 9839.26 | L22: 9839.26
A23: 57 | B23: IMG_0065 | C23: CLASS A: GENERAL ITEMS | D23: METHOD RELATED CHARGES | E23: Cranes | F23: 10t Crane | G23: week | H23: 40 | I23: 1558.2 | J23: 3307.2 | L23: 4865.4
A24: 59 | B24: IMG_0065 | C24: CLASS A: GENERAL ITEMS | D24: METHOD RELATED CHARGES | E24: Miscellaneous | F24: sawbench | G24: week | J24: 90.74 | L24: 90.74
A25: 60 | B25: IMG_0065 | C25: CLASS A: GENERAL ITEMS | D25: METHOD RELATED CHARGES | E25: Miscellaneous | F25: concrete vibrator | G25: week | J25: 7237.78 | L25: 7237.78
A26: 61 | B26: IMG_0065 | C26: CLASS A: GENERAL ITEMS | D26: METHOD RELATED CHARGES | E26: Miscellaneous | F26: 75 mm 750 l/min pump | G26: week | J26: 314.22 | L26: 314.22
A27: 62 | B27: IMG_0065 | C27: CLASS A: GENERAL ITEMS | D27: METHOD RELATED CHARGES | E27: Miscellaneous | F27: compressor; 22.10 m3/min, 216 kW, four tool | G27: week | J27: 7155.57 | L27: 7155.57
A28: 64 | B28: IMG_0066 | C28: CLASS A: GENERAL ITEMS | D28: METHOD RELATED CHARGES | E28: Plant; Miscellaneous (continued) | F28: plate compactor; 180 kg | G28: week | J28: 196.71 | L28: 196.71
A29: 65 | B29: IMG_0066 | C29: CLASS A: GENERAL ITEMS | D29: METHOD RELATED CHARGES | E29: Plant; Miscellaneous (continued) | F29: towed roller; BW6 | G29: week | J29: 2024.96 | L29: 2024.96
A30: 67 | B30: IMG_0066 | C30: CLASS A: GENERAL ITEMS | D30: METHOD RELATED CHARGES | E30: Excavators etc. | F30: hydraulic backacter; 14.5 tonne; driver + banksman | G30: week | H30: 80 | I30: 2737.98 | J30: 3861.81 | L30: 6599.79
A31: 68 | B31: IMG_0066 | C31: CLASS A: GENERAL ITEMS | D31: METHOD RELATED CHARGES | E31: Excavators etc. | F31: bulldozer; D6; driver | G31: week | H31: 40 | I31: 1795.88 | J31: 6143.86 | L31: 7939.74
A32: 69 | B32: IMG_0066 | C32: CLASS A: GENERAL ITEMS | D32: METHOD RELATED CHARGES | E32: Excavators etc. | F32: loading shovel; CAT 939; driver | G32: week | H32: 40 | I32: 1558.2 | J32: 3133.7 | L32: 4691.9
A33: 73 | B33: IMG_0066 | C33: CLASS A: GENERAL ITEMS | D33: METHOD RELATED CHARGES | E33: Supervision for the duration of construction; Time Related Charge | F33: Agent | G33: week | H33: 40 | I33: 3438.18 | L33: 3438.18
A34: 74 | B34: IMG_0066 | C34: CLASS A: GENERAL ITEMS | D34: METHOD RELATED CHARGES | E34: Supervision for the duration of construction; Time Related Charge | F34: Senior Engineer | G34: week | H34: 40 | I34: 2952.89 | L34: 2952.89
A35: 75 | B35: IMG_0066 | C35: CLASS A: GENERAL ITEMS | D35: METHOD RELATED CHARGES | E35: Supervision for the duration of construction; Time Related Charge | F35: Engineers | G35: week | H35: 40 | I35: 2222.32 | L35: 2222.32
A36: 76 | B36: IMG_0066 | C36: CLASS A: GENERAL ITEMS | D36: METHOD RELATED CHARGES | E36: Supervision for the duration of construction; Time Related Charge | F36: General Foreman | G36: week | H36: 40 | I36: 2745.59 | L36: 2745.59
A37: 78 | B37: IMG_0066 | C37: CLASS A: GENERAL ITEMS | D37: METHOD RELATED CHARGES | E37: Administration for the duration of construction; Time Related Charge | F37: Office manager/Cost clerk | G37: week | H37: 40 | I37: 1562.95 | L37: 1562.95
A38: 79 | B38: IMG_0066 | C38: CLASS A: GENERAL ITEMS | D38: METHOD RELATED CHARGES | E38: Administration for the duration of construction; Time Related Charge | F38: Timekeeper/Storeman/Checker | G38: week | H38: 40 | I38: 937.35 | L38: 937.35
A39: 80 | B39: IMG_0066 | C39: CLASS A: GENERAL ITEMS | D39: METHOD RELATED CHARGES | E39: Administration for the duration of construction; Time Related Charge | F39: Typist/Telephonist | G39: week | H39: 40 | I39: 1273.89 | L39: 1273.89
A40: 81 | B40: IMG_0066 | C40: CLASS A: GENERAL ITEMS | D40: METHOD RELATED CHARGES | E40: Administration for the duration of construction; Time Related Charge | F40: Security guard | G40: week | H40: 40 | I40: 888.29 | L40: 888.29
A41: 82 | B41: IMG_0066 | C41: CLASS A: GENERAL ITEMS | D41: METHOD RELATED CHARGES | E41: Administration for the duration of construction; Time Related Charge | F41: Quantity Surveyor | G41: week | H41: 40 | I41: 2188.03 | L41: 2188.03
A42: 84 | B42: IMG_0066 | C42: CLASS A: GENERAL ITEMS | D42: METHOD RELATED CHARGES | E42: Labour teams for the duration of construction; Time Related Charge | F42: General yard labour (part time); loading and offloading, clearing site rubbish etc.; ganger | G42: week | H42: 40 | I42: 1179.78 | L42: 1179.78
A43: 85 | B43: IMG_0066 | C43: CLASS A: GENERAL ITEMS | D43: METHOD RELATED CHARGES | E43: Labour teams for the duration of construction; Time Related Charge | F43: General yard labour (part time); loading and offloading, clearing site rubbish etc.; four unskilled operatives | G43: week | H43: 160 | I43: 4719.12 | L43: 4719.12
A44: 86 | B44: IMG_0066 | C44: CLASS A: GENERAL ITEMS | D44: METHOD RELATED CHARGES | E44: Labour teams for the duration of construction; Time Related Charge | F44: Maintenance of contractor's own plant; Fitter | G44: week | H44: 40 | I44: 1191.6 | L44: 1191.6
A45: 87 | B45: IMG_0066 | C45: CLASS A: GENERAL ITEMS | D45: METHOD RELATED CHARGES | E45: Labour teams for the duration of construction; Time Related Charge | F45: Maintenance of contractor's own plant; Fitter's Mate | G45: week | H45: 40 | I45: 937.35 | L45: 937.35
A46: 90 | B46: IMG_0066 | C46: CLASS A: GENERAL ITEMS | D46: METHOD RELATED CHARGES | E46: DE-WATERING | F46: 1 nr diesel driven pump (WP 150/60 or similar) complete with allowance of £50 for fuel | G46: day | L46: 144.81
A47: 91 | B47: IMG_0066 | C47: CLASS A: GENERAL ITEMS | D47: METHOD RELATED CHARGES | E47: DE-WATERING | F47: 50 m of 150 mm dia. header pipe | G47: day | L47: 26.66
A48: 92 | B48: IMG_0066 | C48: CLASS A: GENERAL ITEMS | D48: METHOD RELATED CHARGES | E48: DE-WATERING | F48: 35 nr of disposable well points | G48: day | L48: 533.93
A49: 93 | B49: IMG_0066 | C49: CLASS A: GENERAL ITEMS | D49: METHOD RELATED CHARGES | E49: DE-WATERING | F49: 18 m of delivery pipe | G49: day | L49: 12.18
A50: 94 | B50: IMG_0066 | C50: CLASS A: GENERAL ITEMS | D50: METHOD RELATED CHARGES | E50: DE-WATERING | F50: 1 nr diesel driven standby pump | G50: day | L50: 83.82
A51: 95 | B51: IMG_0066 | C51: CLASS A: GENERAL ITEMS | D51: METHOD RELATED CHARGES | E51: DE-WATERING | F51: 1 nr jetting pump with hoses (for installation of wellpoints only) | G51: - | L51: 144.81
A52: 96 | B52: IMG_0066 | C52: CLASS A: GENERAL ITEMS | D52: METHOD RELATED CHARGES | E52: DE-WATERING | F52: attendant labour and plant (2 hrs per day) inclusive of small dumper and bowser) | G52: - | L52: 49.09
A53: 98 | B53: IMG_0066 | C53: CLASS A: GENERAL ITEMS | D53: METHOD RELATED CHARGES | E53: DE-WATERING | F53: Bring to site equipment and remove upon completion Installation costs | G53: item | L53: 6877.27
A54: 99 | B54: IMG_0066 | C54: CLASS A: GENERAL ITEMS | D54: METHOD RELATED CHARGES | E54: DE-WATERING | F54: hire of jetting pump with hoses; 1 day | G54: item | L54: 144.81
A55: 100 | B55: IMG_0066 | C55: CLASS A: GENERAL ITEMS | D55: METHOD RELATED CHARGES | E55: DE-WATERING | F55: purchase of well points; 35 Nr | G55: item | L55: 533.93
A56: 101 | B56: IMG_0066 | C56: CLASS A: GENERAL ITEMS | D56: METHOD RELATED CHARGES | E56: DE-WATERING | F56: labour and plant; 10 hours | G56: item | L56: 490.93
A57: 103 | B57: IMG_0066 | C57: CLASS A: GENERAL ITEMS | D57: METHOD RELATED CHARGES | E57: Operating costs | F57: hire of pump, header pipe, delivery pipe and standby pump complete with fuel etc. and 2 hours attendant labour and plant | G57: day | L57: 365.65

Sheet Method & Reconciliation
B1: Method & Reconciliation
B2: How each item's cost was derived, and how the derived costs reconcile to the source.
B4: What changed
B5: The source's published all-in rate has been removed as the cost figure. | E5: It is retained on 'Derived Rates' column P, greyed as 'Published rate £ (superseded)', purely so every derivation can be audited. Delete column P if you want it gone entirely.
B6: Cost is now built up as Labour + Plant + Material. | E6: Column M 'DERIVED COST £' is a live formula =ROUND(SUM(I:L),2). Edit any component and the cost recalculates.
B7: A fourth column, Sub-contract £, carries specialist packages. | E7: Some CESMM classes are published only as all-in specialist rates with no build-up in the source. Splitting them into L/P/M would be invention, so the rate is carried whole in Sub-contract and flagged.
B8: Costs converted to an Irish basis. | E8: Each resource category is factored separately and converted to euro — see the 'Irish Basis' sheet. Labour carries a researched Ireland/UK differential; plant and material sit at parity as stated assumptions. Columns N to R hold the euro figures and are live formulas off that sheet.
B9: Preliminaries excluded. | E9: CESMM Class A: General Items (53 items) moved to 'Preliminaries (Excluded)'.
B10: Resource build-ups separated. | E10: 543 rows that looked like rates are actually labour-gang and plant hourly build-ups (the inputs behind the rates). Moved to 'Resource Rates' so they are not double-counted as priceable items.
B12: Derivation basis — counts
B13: Basis | C13: Items | D13: % of items | E13: What it means
B14: Stated build-up | C14: 2891 | D14: 76.2% | E14: Labour, plant and material all published and reconciling to the published rate. Cost is taken straight from the build-up.
B15: Material recovered as residual | C15: 27 | D15: 0.7% | E15: Labour and plant published, material column missing from the source, but the published rate contains it. Material = rate − labour − plant. Verified against identical operations in the same section that do carry a material figure.
B16: Stated components + specialist balance | C16: 52 | D16: 1.4% | E16: Published plant (and sometimes labour) retained as real; the remaining balance of a specialist all-in rate is not broken down at source and sits in Sub-contract.
B17: Apportioned (sub-heading) | C17: 11 | D17: 0.3% | E17: No build-up published. Rate split using the median labour/plant/material shares of 3+ comparable build-ups in the same sub-heading.
B18: Apportioned (section) | C18: 116 | D18: 3.1% | E18: As above, using 5+ comparable build-ups in the same section.
B19: Apportioned (class) | C19: 95 | D19: 2.5% | E19: As above, using 10+ comparable build-ups elsewhere in the same CESMM class. Weakest apportionment — all such rows are in the Review Queue.
B20: All-in specialist rate | C20: 601 | D20: 15.8% | E20: Classes B, C, D, M, P and T (ground investigation, geotechnical processes, demolition, structural metalwork, piling, tunnelling) plus testing and professional-services sections. Spon's publishes these as sub-contract packages with no build-up, so the whole rate sits in Sub-contract, unsplit.
B21: TOTAL | C21: 3793 | D21: 100.0%
B23: Confidence
B24: Confidence | C24: Items | D24: % of items | E24: Basis
B25: High | C25: 2891 | D25: 76.2% | E25: Cost is the source's own published build-up.
B26: Medium-High | C26: 27 | D26: 0.7% | E26: One component recovered arithmetically and cross-checked against comparable items.
B27: Medium | C27: 179 | D27: 4.7% | E27: Apportioned from close comparables, or a specialist rate with real published components.
B28: Low | C28: 95 | D28: 2.5% | E28: Apportioned from class-level comparables only — treat as indicative.
B29: All-in (not split) | C29: 601 | D29: 15.8% | E29: Total cost is correct and equals the published rate; the labour/plant/material split does not exist in the source and has not been invented.
B31: Reconciliation to source (live formulas over 'Derived Rates')
B32: Check | C32: Value | E32: Expected
B33: Priceable items carried | C33: =COUNTA('Derived Rates'!A5:A3797) | E33: 3,793 — every non-preliminary, non-resource rate row
B34: Control total — UK cost (£) | C34: =ROUND(SUM('Derived Rates'!M5:M3797),2) | E34: RECONCILIATION ONLY — this adds together rates in different units (£/m, £/nr, £/m3), so it is not a project cost. Its only purpose is to prove that no cost was lost or invented in the derivation.
B35: Control total — published rates (£) | C35: =ROUND(SUM('Derived Rates'!U5:U3797),2) | E35: The same sum over the superseded published rates.
B36: Total variance (derived − published) | C36: =ROUND(SUM('Derived Rates'!M5:M3797)-SUM('Derived Rates'!U5:U3797),2) | E36: £0.00 — the derivation reallocates cost between resource categories, it does not change it
B37: Items where derived ≠ published (>1p) | C37: =COUNTIF('Derived Rates'!V5:V3797,">0.01")+COUNTIF('Derived Rates'!V5:V3797,"<-0.01") | E37: 0 — every item should reconcile
B38: Control total — IRISH cost (€) | C38: =ROUND(SUM('Derived Rates'!R5:R3797),2) | E38: The same control total after the Irish factors and GBP→EUR conversion on the 'Irish Basis' sheet.
B39: Total Labour (£) | C39: =ROUND(SUM('Derived Rates'!I5:I3797),2)
B40: Total Plant (£) | C40: =ROUND(SUM('Derived Rates'!J5:J3797),2)
B41: Total Material (£) | C41: =ROUND(SUM('Derived Rates'!K5:K3797),2)
B42: Total Sub-contract, unsplit specialist (£) | C42: =ROUND(SUM('Derived Rates'!L5:L3797),2)
B43: Items flagged for review | C43: =COUNTIF('Derived Rates'!W5:W3797,"?*") | E43: Listed on the 'Review Queue' sheet
B45: Cost mix where the source publishes a real build-up
B46: Resource | C46: Share | E46: Basis
B47: Labour | C47: 0.2137 | E47: Measured across the 2,881 items the source builds up in full, excluding a handful of very large rail-track lump sums that would otherwise dominate. This is the meaningful cost mix for this book.
B48: Plant | C48: 0.1074
B49: Material | C49: 0.6789
B50: Note on the whole-file mix | E50: Across all 3,793 items, sub-contract is ~94% of the control total. That figure is an artefact of a few very large specialist lump sums (tunnel shafts, viaduct piers) and is not a useful mix — use the shares above instead.
B52: Caveats
B53: • | E53: Source is an OCR extraction of Spon's Civil Engineering and Highway Works Price Book, so some figures are mis-read. 2 rows are an order of magnitude out of line with their class and are flagged 'Probable source error'; 6 more sit far from comparable items; 8 are very large unit rates worth checking. Scanning error may remain elsewhere.
B54: • | E54: Rates are net cost — the source's published rate already excludes oncosts and profit, which Spon's adds separately. Nothing here carries overhead, profit, or preliminaries.
B55: • | E55: Apportioned splits are statistical, not quoted. They preserve the correct total cost but the labour/plant/material shares are estimates from comparable items.
B56: • | E56: Sub-contract rows are correct in total. They are not zero-labour items — the labour simply sits inside a specialist's price.
B57: • | E57: Gang hours are carried through unchanged from the source as supporting information.
B58: • | E58: The Irish conversion is a factor applied to UK build-ups, not Irish quoted rates. The labour factor is well grounded in statutory rates both sides; the plant and material factors are parity assumptions because no published Ireland-vs-UK price-level comparison exists. Treat the euro figures as a defensible starting point to be tested against Irish supplier and hire-desk quotes, not as tender-ready rates.
B59: • | E59: Irish rates exclude VAT and the sub-contractor's own margin, on the same basis as the UK figures.
